Workbook

Sheet % Consulta pré anestésica
A1: ANO | C1: 2025
A2: TAXA DE PROCEDIMENTOS ELETIVOS COM CONSULTA PRÉ-ANESTÉSICA AMBULATORIAL | C2: =C4/C5 -> 0.79517191 | D2: =D4/D5 -> 0.79330007 | E2: =E4/E5 -> 0.75690236 | F2: =F4/F5 -> 0.84649123 | G2: =G4/G5 -> 0.85654513 | H2: =H4/H5 -> 0.96018277 | I2: =I4/I5 -> 0.95281996 | J2: =J4/J5 -> 0.97834758 | K2: =K4/K5 -> 0.97022198 | O2: =MEDIAN(C2:N2) -> 0.85654513
A3: MÊS | C3: Janeiro | D3: Fevereiro | E3: Março | F3: Abril | G3: Maio | H3: Junho | I3: Julho | J3: Agosto | K3: Setembro | L3: Outubro | M3: Novembro | N3: Dezembro | O3: MÉDIA ANUAL
A4: Nº de pacientes submetidos a procedimentos eletivos sob anestesia/sedação com realização de consulta pré-anestésica ambulatorial. | C4: 1087 | D4: 1113 | E4: 1124 | F4: 1351 | G4: 1433 | H4: 1471 | I4: 1757 | J4: 1717 | K4: 1792 | L4: 0 | M4: 0 | N4: 0 | O4: =MEDIAN(C4:N4) -> 1237.5
A5: Nº de pacientes submetidos a procedimentos eletivos sob anestesia/sedação. | C5: 1367 | D5: 1403 | E5: 1485 | F5: 1596 | G5: 1673 | H5: 1532 | I5: 1844 | J5: 1755 | K5: 1847 | L5: 0 | M5: 0 | N5: 0 | O5: =MEDIAN(C5:N5) -> 1508.5
A6: Meta | C6: > 95%
A7: MÊS | B7: Análise Critica | D7: Plan (Planejar) | G7: Do (Executar/Fazer) | J7: Check (Verificar/Checar) | M7: Act (Agir/Ajustar/Padronizar)
A8: 1º Trimestre (Jan–Fev–Mar) | B8: O indicador manteve desempenho significativamente abaixo da meta (>95%), com resultados de 79%, 78% e 74%, representando deterioração progressiva do processo. Entre janeiro e março, o total de procedimentos eletivos sob anestesia/sedação aumentou 7% (de 1.400 para 1.501), mas o número de consultas pré-anestésicas ambulatoriais não acompanhou essa expansão, crescendo apenas 1% (de 1.099 para 1.109). O Centro Cirúrgico concentrou a maior parte das falhas — grande volume de avaliações realizadas no dia da cirurgia e ausência de registro eletrônico formal. O Serviço de Imagem, embora com média de 636 exames anestésicos por mês, apresentava apenas 50% de cobertura de consulta prévia (média de 308 consultas). As falhas de comunicação entre equipes e inconsistências nos consentimentos anestésicos impactaram a confiabilidade do dado. | D8: Reestruturar o fluxo de consulta pré-anestésica ambulatorial com definição de critérios obrigatórios de agendamento e responsabilidades entre anestesia, cirurgia e marcação cirúrgica. Criar rotina mínima de 48h para avaliação prévia e padronizar os registros em instrumento único. Iniciar a implantação de sistema informatizado (Axreg) para rastreabilidade e controle. | G8: Ações pontuais de sensibilização das equipes e reuniões operacionais com anestesistas e enfermagem para revisar o fluxo de marcação. As auditorias clínicas foram iniciadas, porém com baixa abrangência e sem padronização de indicadores. O processo de agendamento permaneceu majoritariamente manual. | J8: O desempenho manteve-se abaixo da meta, sem evolução significativa. Houve subnotificação e falhas de rastreabilidade, com predominância de registros manuais e ausência de integração entre setores. As falhas mais críticas envolveram consultas não sinalizadas e inconsistências em termos de consentimento. | M8: Iniciar revisão estrutural do processo com definição clara de responsabilidades e implantação piloto do Axreg. Criar protocolo institucional de consulta pré-anestésica obrigatória para todos os procedimentos eletivos e monitoramento sistemático por auditoria clínica.
A11: 2º Trimestre (Abr–Mai–Jun) | B11: O segundo trimestre apresentou tendência de recuperação — o indicador evoluiu de 84% em abril para 93% em junho, o melhor resultado do semestre. O número de procedimentos eletivos sob anestesia aumentou de 1.601 para 1.550 (-3%), enquanto as consultas prévias cresceram 7% (de 1.351 para 1.446), sinalizando melhor aderência ao protocolo. O Centro Cirúrgico manteve crescimento na proporção de pacientes avaliados antes do procedimento (802 em abril para 788 em junho). O Serviço de Imagem apresentou ganho expressivo: 672 exames anestésicos em abril e 612 em junho, com aumento das consultas prévias de 482 para 600. As auditorias mostraram redução nas falhas documentais e maior comunicação entre setores, embora a meta de 95% ainda não tenha sido alcançada. | D11: Consolidar a padronização dos fluxos de avaliação pré-anestésica, com foco em adesão integral das equipes e rastreabilidade eletrônica via Axreg. Definir rotina mensal de auditorias e reforçar a comunicação intersetorial. Estabelecer metas intermediárias de 90% e 93% até o atingimento da meta de 95%. | G11: Houve maior engajamento operacional: reuniões de alinhamento com equipes, capacitações sobre o protocolo e início do uso formal do Axreg em parte dos serviços. As auditorias clínicas passaram a acompanhar a execução do fluxo. | J11: O desempenho de 93% em junho confirmou o impacto das ações implementadas, com redução das falhas de registro e avanço na rastreabilidade. Contudo, persistiram falhas de sinalização no sistema e casos isolados de pareceres realizados no centro cirúrgico. | M11: Reforçar o uso obrigatório do Axreg em todos os serviços (centro cirúrgico, obstétrico e imagem). Formalizar POP institucional de pré-anestesia e intensificar as auditorias cruzadas mensais, além de ampliar os treinamentos periódicos.
A14: MÊS | B14: Análise Critica | D14: Plan (Planejar) | G14: Do (Executar/Fazer) | J14: Check (Verificar/Checar) | M14: Act (Agir/Ajustar/Padronizar)
A15: JULHO | B15: O indicador apresentou desempenho de 93%, evidenciando consolidação das melhorias implementadas no semestre anterior e fortalecimento da cultura de segurança perioperatória. Observou-se progressiva adesão das equipes médicas e de enfermagem ao protocolo de consulta pré-anestésica ambulatorial, com destaque para o aumento expressivo dos procedimentos eletivos com pré-consulta (1.741 em julho contra 1.446 em junho) e melhoria da rastreabilidade documental. Houve também ampliação da obrigatoriedade da consulta para exames de imagem sob anestesia, que registraram 804 procedimentos anestésicos, representando avanço na integração entre os setores. Entretanto, persistiram falhas no uso do sistema Axreg, com registros incompletos e consultas realizadas no mesmo dia do procedimento, além da ausência de padronização plena nos lançamentos, o que impactou a mensuração do indicador. | D15: Garantir que 95% dos pacientes submetidos a procedimentos eletivos sob anestesia/sedação realizem consulta pré-anestésica ambulatorial, assegurando o alcance da meta ≥95%. Implementar ações voltadas à sensibilização dos cirurgiões sobre o fluxo de agendamento e prazos mínimos, promover a adoção obrigatória do sistema Axreg como ferramenta oficial de registro e fortalecer a integração entre marcação cirúrgica, anestesia e enfermagem por meio de reuniões de bate-mapa. | G15: Foram executadas ações para fortalecer o cumprimento do protocolo, com ênfase na padronização dos fluxos e na qualificação das equipes. Reforçou-se a obrigatoriedade da consulta pré-anestésica também para exames de imagem, endoscopias, colonoscopias sob anestesia, ampliando a cobertura do processo. As equipes foram sensibilizadas quanto ao correto registro no Axreg, consolidado como ferramenta oficial de rastreabilidade. A integração intersetorial foi intensificada no bate-mapa, permitindo melhor planejamento e redução de falhas. | J15: O resultado de 93% manteve evolução consistente em relação aos meses anteriores, demonstrando maior adesão das equipes, porém ainda abaixo da meta. As auditorias evidenciaram avanços na organização do fluxo e na execução das consultas, mas persistiram falhas operacionais, especialmente na utilização do Axreg e na subcaptura de dados. A confiabilidade do indicador ainda depende de ajustes na padronização e na integração do sistema com o Hospital Unimed Chapecó. | M15: Adotar medidas corretivas e de padronização para consolidar o processo e alcançar a meta. Tornar obrigatório o registro das consultas no Axreg, com bloqueio de agendamento sem o devido lançamento. Revisar e uniformizar o fluxo documental, fortalecer auditorias cruzadas mensais e implementar capacitação contínua das equipes médicas, de enfermagem e administrativas, consolidando a padronização institucional.
A16: AGOSTO | B16: O indicador apresentou desempenho satisfatório em 97%, superando a meta institucional e refletindo o impacto positivo das ações corretivas adotadas nos meses anteriores. O resultado demonstra avanço consolidado na adesão das equipes médicas e de enfermagem as ações voltadas ao protocolo, embora ainda existam margens de melhoria na estabilidade e padronização dos registros. Observou-se ampliação do uso do Axreg, com redução de inconsistências documentais. No serviço de imagem, 767 procedimentos anestésicos foram realizados, todos com avaliação ou consulta prévia, reforçando a consolidação do fluxo. Entretanto, o processo ainda requer ajustes na coleta e integração dos dados, garantindo sustentabilidade e confiabilidade das informações. | D16: Garantir a realização da consulta pré-anestésica ambulatorial para todos dos pacientes submetidos a procedimentos eletivos e exames de imagem sob anestesia, mantendo o desempenho acima da meta institucional (≥95%). Consolidar o uso obrigatório do sistema Axreg como ferramenta única de registro, revisar periodicamente os fluxos intersetoriais e reforçar a educação permanente das equipes quanto à rastreabilidade e à importância do planejamento pré-operatório | G16: Foram intensificadas as auditorias clínicas e acompanhamentos operacionais para monitorar a adesão ao protocolo. As equipes de anestesia e enfermagem atuaram de forma integrada no bate-mapa, assegurando alinhamento entre agendamentos e consultas. O uso do Axreg foi amplamente incorporado, reduzindo falhas de documentação e garantindo a obrigatoriedade da consulta também para exames de imagem sob anestesia ou sedação. | J16: O resultado de 97% representa superação da meta e comprova a efetividade das ações implementadas. Houve uma significativa redução de inconsistências e a adesão consolidada ao uso do Axreg. A integração entre marcação cirúrgica e anestesia mostrou-se estável e eficaz. | M16: Será reavaliado ainda a busca dos dados do indicador junto a unimed chapecó. O Axreg será mantido como sistema oficial e obrigatório de registro das avaliações pré-anestésicas, abrangendo cirurgias e exames de imagem. Permanecem as auditorias cruzadas mensais e o acompanhamento intersetorial, além da educação continuada das equipes para garantir sustentabilidade, qualidade assistencial e cultura de conformidade.
A17: SETEMBRO | B17: O indicador manteve-se dentro da meta institucional, atingindo 95% em setembro, demonstrando estabilidade do desempenho e sustentação dos avanços obtidos nos meses anteriores, embora com leve queda em relação a agosto (97%). A variação está associada ao aumento do volume assistencial, com 1021 pacientes atendidos no centro cirúrgico, sendo 896 procedimentos eletivos e 854 anestesias realizadas. O serviço de imagem também registrou 4710 atendimentos, com 830 procedimentos anestésicos, todos com consulta prévia. Apesar da boa adesão, ainda foram observadas inconsistências no registro das avaliações pré anestesicas no Axreg, especialmente nas realizadas previamente antes do procedimento cirúrgico. | D17: Manter o indicador acima da meta de 95%, consolidando a prática da consulta pré-anestésica ambulatorial para todos os pacientes eletivos e exames de imagem sob anestesia. Reforçar a padronização dos registros no Axreg e o controle das avaliações pré anestesicas através da utilização do axReg. Garantir uniformidade na coleta e análise de dados e promover ações educativas contínuas voltadas à sustentabilidade do processo. | G17: Foram mantidas as ações operacionais e de auditoria, com reforço no acompanhamento das agendas de consulta e anestesia. As equipes atuaram de forma integrada no bate-mapa, ajustando fluxos diante do aumento de volume. O uso do Axreg foi ampliado e tornou-se obrigatória a consulta ou avaliação pré anestesica também para exames de imagem. | J17: O resultado de 95% confirma o cumprimento da meta e a manutenção do processo em patamar estável, apesar do crescimento da demanda. Observou-se boa adesão e melhoria contínua na rastreabilidade, mas ainda persistem falhas pontuais na padronização e integração sistêmica dos dados. | M17: Implementar padronização definitiva do fluxo de registro e coleta de dados no Axreg, com automação entre o sistema de agendamento cirúrgico e o de imagem. Fortalecer auditorias cruzadas intersetoriais e instituir checagem eletrônica obrigatória antes do agendamento. Manter capacitações mensais com foco em consolidação da governança clínica e sustentabilidade dos resultados.
A18: MÊS | B18: Análise Critica | D18: Plan (Planejar) | G18: Do (Executar/Fazer) | J18: Check (Verificar/Checar) | M18: Act (Agir/Ajustar/Padronizar)
A19: OUTUBRO
A20: NOVEMBRO
A21: DEZEMBRO

Sheet % Incidencia de dor aguda
A1: INCIDÊNCIA DE DOR AGUDA NO PERÍODO INTRAOPERATÓRIO ATÉ A ALTA ANESTÉSICA | C1: 2025
C2: =C4/C5 -> 0.050951087 | D2: =D4/D5 -> 0.043648208 | E2: =E4/E5 -> 0.040443575 | F2: =F4/F5 -> 0.034525277 | G2: =G4/G5 -> 0.059738643 | H2: =H4/H5 -> 0.033333333 | I2: =I4/I5 -> 0.035934868 | J2: =J4/J5 -> 0.03372093 | K2: =K4/K5 -> 0.036752606 | O2: =+MEDIAN(C2:N2) -> 0.036752606
A3: MÊS | C3: Janeiro | D3: Fevereiro | E3: Março | F3: Abril | G3: Maio | H3: Junho | I3: Julho | J3: Agosto | K3: Setembro | L3: Outubro | M3: Novembro | N3: Dezembro | O3: MÉDIA ANUAL
A4: Nº de pacientes que apresentaram dor aguda no período intraoperatório até a alta anestésica da SRPA ou transferência para UTI. | C4: 75 | D4: 67 | E4: 62 | F4: 56 | G4: 96 | H4: 51 | I4: 64 | J4: 58 | K4: 67 | L4: 0 | M4: 0 | N4: 0 | O4: =+MEDIAN(C4:N4) -> 60
A5: Nº de pacientes submetidos a procedimentos sob anestesia/sedação. | C5: 1472 | D5: 1535 | E5: 1533 | F5: 1622 | G5: 1607 | H5: 1530 | I5: 1781 | J5: 1720 | K5: 1823 | L5: 0 | M5: 0 | N5: 0 | O5: =+MEDIAN(C5:N5) -> 1534
A6: META | C6: <5%
A7: MÊS | B7: Análise Critica | D7: Plan (Planejar) | G7: Do (Executar/Fazer) | J7: Check (Verificar/Checar) | M7: Act (Agir/Ajustar/Padronizar)
A8: JANEIRO | B8: O mês apresentou incidência de 5% de pacientes com dor intensa ou insuportável e de difícil controle, situando-se no limite da meta estabelecida (<5%). Foram 75 casos de dor intensa entre 1.472 pacientes anestesiados, evidenciando fragilidade no manejo analgésico intra e pós-operatório imediato. Apesar de 793 pacientes (54%) não relatarem dor e 121 (8%) apresentarem dor leve a moderada, o número de casos graves ainda indica inconsistência na efetividade da analgesia preventiva. As auditorias apontaram ausência de padronização de condutas analgésicas, uso irregular de escalas de dor e planos anestésicos genéricos, sem individualização conforme o tipo cirúrgico. Além disso, a falha de comunicação entre o centro cirúrgico e a SRPA contribuiu para o subtratamento analgésico no pós-operatório. | D8: Diante do resultado de 5% em janeiro e da manutenção acima do nível ideal, foi identificada a necessidade de estruturar um plano de ação voltado à uniformização do manejo analgésico, tanto intraoperatório quanto na SRPA. As auditorias apontaram ausência de protocolo institucional, uso irregular das escalas de dor, planos anestésicos pouco individualizados e falhas na comunicação entre anestesia e enfermagem. O objetivo definido foi reduzir a incidência de dor aguda abaixo de 4%, com melhor registro e avaliação sistemática da dor. | G8: Neste trimestre, as ações foram pontuais e não sistematizadas. Houve iniciativas isoladas de anestesistas para ajustar analgesia conforme tipo cirúrgico e orientações informais durante os plantões, mas sem formalização institucional. | J8: A análise dos resultados mostrou pequena redução na taxa de dor intensa, mas sem estabilidade. Janeiro apresentou 5% (75 casos/1.472 anestesias), Fevereiro reduziu para 4% (67 casos/1.535), Março manteve 4% (62 casos/1.533). O período apresentou instabilidade do indicador, baixa adesão protocolo e incosistencias analgésica. Houve avanços pontuais, mas sem consolidação de resultados sustentáveis. | M8: Com base nos achados, foram definidas ações estruturadas para o trimestre seguinte, incluindo a elaboração e implantação de um protocolo de avaliação e controle da dor aguda perioperatória, padronização do uso da escala EVA, capacitação das equipes de anestesia e enfermagem, e revisão dos fluxos de comunicação entre o centro cirúrgico e a SRPA. Também foi proposta a inclusão do tema nas auditorias clínicas mensais, como forma de reforçar o monitoramento contínuo do processo.
A9: FEVEREIRO | B9: Houve leve redução da incidência para 4% (67 casos/1.535 anestesias), mantendo o indicador próximo da meta. A maior parte dos pacientes, 810 (53%), permaneceu sem relato de dor, enquanto 121 (8%) apresentaram dor leve a moderada. A diminuição dos casos graves demonstra avanço discreto, porém persistem falhas na avaliação sistemática da dor e na reavaliação em SRPA, com uso não padronizado das escalas. Parte dos pacientes recebeu analgesia inadequada ao tipo de cirurgia, reforçando fragilidade no manejo analgésico de procedimentos regionais.
A10: MARÇO | B10: O mês manteve incidência de 4% (62 casos/1.533 anestesias), sem avanço expressivo no controle da dor. Do total de pacientes, 801 (52%) não apresentaram dor, enquanto 147 (10%) referiram dor leve a moderada. Embora o percentual de dor intensa tenha se mantido estável, houve relatos de subnotificação de dor leve, sugerindo que o controle e o registro ainda não estão consolidados. As auditorias demonstraram adesão parcial ao protocolo de manejo da dor aguda, porém persistem fragilidades nas intervenções analgésicas, especialmente nas anestesias regionais.
A11: MÊS | B11: Análise Critica | D11: Plan (Planejar) | G11: Do (Executar/Fazer) | J11: Check (Verificar/Checar) | M11: Act (Agir/Ajustar/Padronizar)
A12: ABRIL | B12: Observou-se melhora significativa no controle da dor, com redução da incidência para 3% (56 casos/1.622 anestesias). A maioria dos pacientes, 896 (55%), não apresentou dor, e 125 (8%) relataram dor leve a moderada, indicando melhor equilíbrio entre prevenção e tratamento analgésico. Apesar do avanço, persistem falhas pontuais na documentação das reavaliações e instabilidade no registro da intensidade da dor. As auditorias evidenciaram adesão crescente das equipes e melhor comunicação entre anestesia e SRPA, com início do uso sistemático de escalas de dor (EVA) por parte de alguns profissionais. | D12: "A partir da análise do primeiro trimestre, o planejamento concentrou-se em institucionalizar o protocolo de dor aguda, fortalecer a comunicação entre anestesia e SRPA e garantir reavaliações sistemáticas com registro em prontuário. O foco foi consolidar a uniformidade de condutas analgésicas e reduzir a variabilidade entre profissionais e turnos." | G12: "No decorrer do segundo trimestre, houve aumento da adesão ao uso da escala EVA e melhor integração entre as equipes multiprofissionais. Os anestesistas passaram a aplicar condutas analgésicas mais individualizadas, especialmente em cirurgias ortopédicas e ginecológicas, e a documentação na SRPA tornou-se mais consistente. A abertura do ambulatorio de dor e a incorporação de um anestesista especialista em dor ao serviço junto com as discussões e apresentações dos dados e auditorias começaram a gerar engajamento visível entre as equipes." | J12: "Os resultados demonstraram tendência clara de melhoria, com estabilização próxima à meta institucional: Abril apresentou 3% (56 casos/1.622 anestesias), refletindo as primeiras melhorias estruturais; Maio teve retrocesso para 6% (96 casos/1.607), possivelmente associado ao aumento de volume e complexidade cirúrgica; Junho recuperou o desempenho, voltando a 3% (51 casos/1.530). A média trimestral foi 4%, consolidando o indicador dentro da meta, porém ainda com dependência de reforço educativo e auditoria sistemática. Houve redução de variação e melhoria significativa dos resultados. Ainda que o pico de maio revele vulnerabilidade operacional, o semestre encerra com tendência de consolidação." | M12: "Com base na consolidação dos resultados, o trimestre encerrou com a formalização do protocolo institucional de dor aguda e a inclusão do tema nas auditorias clínicas periódicas. As próximas etapas envolvem monitoramento contínuo dos registros em SRPA, feedback estruturado aos anestesistas e equipes de enfermagem, e revisão periódica das condutas analgésicas por tipo de cirurgia." .
A13: MAIO | B13: O mês representou um retrocesso no desempenho, com aumento da taxa para 6% (96 casos/1.607 anestesias) — elevação de 2% em relação ao mês anterior. Entre os pacientes avaliados, 888 (55%) não apresentaram dor e 154 (10%) relataram dor leve a moderada, sugerindo desequilíbrio no controle analgésico. O aumento pode estar relacionado ao crescimento do número e da complexidade dos procedimentos, e as auditorias evidenciaram falhas na administração de analgesia e no monitoramento da dor em pacientes transferidos para UTI, além da ausência de registros de intervenções analgésicas adequadas.
A14: JUNHO | B14: O indicador retornou ao patamar de 3% (51 casos/1.530 anestesias), mostrando recuperação do controle analgésico. A maioria dos pacientes, 874 (57%), não apresentou dor, enquanto 139 (9%) relataram dor leve a moderada. Esses dados indicam maior aderência às estratégias analgésicas e melhoria na atuação das equipes de enfermagem e anestesia, com registros mais completos das escalas de dor. Contudo, a abordagem ainda carece de sistematização plena, com falhas observadas na continuidade da analgesia, especialmente em procedimentos realizados no final dos turnos.
A15: MÊS | B15: Análise Critica | D15: Plan (Planejar) | G15: Do (Executar/Fazer) | J15: Check (Verificar/Checar) | M15: Act (Agir/Ajustar/Padronizar)
A16: JULHO | B16: O mês manteve 4% (64 casos/1.781 anestesias), dentro da meta, embora com pequeno aumento em relação ao mês anterior. Entre os pacientes, 946 (53%) não apresentaram dor e 124 (7%) tiveram dor leve a moderada, o que sugere estabilidade clínica, porém necessidade de maior uniformidade na avaliação da dor. As auditorias mostraram melhor padronização das condutas e maior consistência documental, e nesse período iniciou-se a revisão do protocolo de dor, em conjunto com a equipe hospitalar e o ambulatório de dor. | D16: O planejamento do trimestre concentrou-se na revisão do protocolo institucional de dor e implantação do ambulatorio , aprimorado a partir dos resultados do semestre anterior. O objetivo foi garantir adesão integral das equipes, fortalecer a rastreabilidade dos registros e incorporar a avaliação da dor aos painéis de desempenho assistencial | G16: "Durante o período, foram realizadas reuniões multiprofissionais de revisão e validação do protocolo, alinhamentos formais sobre registro e reavaliação da dor, e implantação gradativa do novo formulário de acompanhamento em SRPA. As equipes mantiveram uso consistente da escala EVA, e o ambulatório iniciou sua atuação no tratamento dor de casos críticos e revisão de condutas analgésicas." | J16: "Os resultados confirmaram manutenção da estabilidade do indicador, melhor uniformidade das práticas e melhoria contínua na documentação. O processo analgésico apesar de ter apresentado redução de variabilidade, ainda é um desafio a ser superado." | M16: O protocolo foi revisado e descrito pelo anestesiologista especialista em dor, e atualmente segue em análise pela equipe de farmácia, com o objetivo de garantir a padronização das medicações analgésicas utilizadas. As ações para o próximo trimestre estarão concentradas na capacitação das equipes multiprofissionais e na implantação efetiva do novo protocolo institucional de dor aguda, assegurando alinhamento técnico, segurança medicamentosa e consolidação das práticas assistenciais padronizadas.
A17: AGOSTO | B17: Embora a nova versão do protocolo ainda não tenha sido implantada, o indicador apresentou 3% (58 casos/1.720 anestesias), correspondendo ao melhor resultado do semestre. A maioria dos pacientes, 917 (53%), não relatou dor, enquanto 147 (9%) apresentaram dor leve a moderada, indicando melhor controle analgésico e adesão consolidada às condutas existentes. As auditorias evidenciaram documentação consistente e intervenções adequadas, com manutenção da segurança e conforto perioperatório.
A18: SETEMBRO | B18: O mês manteve 4% (67 casos/1.823 anestesias), permanecendo dentro da meta e demonstrando controle efetivo da dor durante o período intra e pós-anestésico. A maior parte dos pacientes, 950 (52%), não apresentou dor, enquanto 110 (6%) relataram dor leve a moderada, confirmando estabilidade do manejo analgésico. As auditorias identificaram poucas falhas, relacionadas à subnotificação de dor leve e inconsistências em cirurgias de curta duração. O controle analgésico mostrou-se efetivo e seguro, sem intercorrências relevantes.

Sheet % Abreviação do jejum P.
A1: INCIDÊNCIA DE ABREVIAÇÃO DO JEJUM PROLONGADO | C1: 2025
C2: 0.32 | D2: 0.35 | E2: 0.32 | F2: 0.41 | G2: 0.38 | H2: 0.4 | I2: 0.4 | J2: 0.43 | K2: 0.42 | O2: =MEDIAN(C2:N2) -> 0.4
A3: MÊS | C3: Janeiro | D3: Fevereiro | E3: Março | F3: Abril | G3: Maio | H3: Junho | I3: Julho | J3: Agosto | K3: Setembro | L3: Outubro | M3: Novembro | N3: Dezembro | O3: Média anual
A4: N° de pacientes que receberam o suplemento para abreviação do jejum prolongado | C4: 191 | D4: 208 | E4: 221 | F4: 295 | G4: 309 | H4: 334 | I4: 293 | J4: 366 | K4: 360 | L4: 0 | M4: 0 | N4: 0 | O4: =MEDIAN(C4:N4) -> 257
A5: N° de pacientes inclusos no protocolo de abreviação de Jejum | C5: 600 | D5: 599 | E5: 689 | F5: 728 | G5: 804 | H5: 827 | I5: 728 | J5: 842 | K5: 851 | L5: 0 | M5: 0 | N5: 0 | O5: =MEDIAN(C5:N5) -> 708.5
A6: META | C6: >60%
A7: MÊS | B7: Análise Critica | D7: Plan (Planejar) | G7: Do (Executar/Fazer) | J7: Check (Verificar/Checar) | M7: Act (Agir/Ajustar/Padronizar)
A8: Janeiro | B8: O mês de janeiro apresentou uma adesão muito abaixo da meta estabelecida, com apenas 32% dos pacientes incluídos no protocolo recebendo o suplemento. A análise das auditorias revelou diversas falhas sistêmicas, especialmente nos casos de internações por urgência/emergência, onde não houve registro de avaliação pré-anestésica nem prescrição do suplemento. Houve ainda subutilização do protocolo entre pacientes eletivos, mesmo com critérios de inclusão claros. Muitos pacientes com consulta anestésica agendada não tiveram o suplemento prescrito ou administrado, e quando houve indicação, a recusa do paciente não foi devidamente registrada ou gerenciada. A ausência de integração entre a prescrição médica e a execução de enfermagem comprometeu significativamente os resultados. | D8: Durante o trimestre, a adesão manteve-se entre 32% e 35%, muito abaixo da meta institucional de >60%, indicando falhas estruturais e não apenas operacionais. As auditorias apontaram ausência de integração entre prescrição médica, execução de enfermagem e registro em prontuário eletrônico, bem como baixa rastreabilidade do processo. Principais causas identificadas: Falta de padronização do fluxo assistencial entre anestesia, enfermagem e nutrição. Prescrição ausente ou não concretizada na consulta pré-anestesica. Subutilização do protocolo em pacientes eletivos e ausência de fluxo adaptado para internações de urgências. Falta de registro formal de recusa e ausência de condutas alternativas. Falhas na avaliação glicêmica e ausência de checagem do horário de administração. Fragmentação da comunicação entre unidades (internação, anestesia e centro cirúrgico). Objetivo: Alcançar mínimo de 45% de adesão ao protocolo até o final do 2º trimestre de 2025, por meio da padronização dos fluxos, capacitação e integração dos registros. | G8: Sensibilização e capacitação técnica: início de treinamento com foco na importância fisiológica do protocolo e impacto clínico do jejum prolongado. Auditorias clínicas mensais: análise amostral de prontuários e entrevistas com equipes de anestesia e enfermagem. Discussão em comitê multidisciplinar para definição de fluxo padrão e identificação de gargalos operacionais. Elaboração de material educativo para pacientes (folder explicativo sobre suplemento e tempo de jejum). Planejamento de inclusão de campo obrigatório no prontuário eletrônico (“Paciente incluído no protocolo / motivo da não adesão”). Resultados parciais: Melhoria discreta em fevereiro, porém sem consolidação. Persistência de falhas na execução prática e no registro da administração. Identificação de resistência de parte da equipe médica e ausência de liderança formal no processo. | J8: Adesão média: 33%, sem tendência de melhoria sustentada. onformidade das auditorias do protocolo: Prescrição (52%) / Administração (48%). As ações pontuais não geraram mudança comportamental nem sistêmica. O processo ainda depende da iniciativa individual ou rotina institucionalizada. | M8: Instituir planilha de acompanhamento/registro do protocolo de abreviação do jejum na consulta pré-anestésica → Prescrição Designar anestesista para lideranças do protocolo. Definir monitoramento mensal com feedback individualizado às equipes envolvidas. Meta para o próximo ciclo (2º trimestre): Elevar adesão média para ≥40%.
A10: Fevereiro | B10: Em fevereiro, observou-se discreta melhora, embora a adesão continue insatisfatória. As falhas persistem, sobretudo na falta de registros que comprovem a inclusão formal dos pacientes no protocolo, mesmo em casos com todos os critérios atendidos. Além disso, alguns pacientes recusaram o suplemento, e essa recusa não foi sucedida por condutas alternativas nem orientações formais. Também foi identificado que a consulta pré-anestésica nem sempre resultava na prescrição do suplemento, o que evidencia a necessidade de padronização do processo e maior engajamento da equipe de anestesia. Em pacientes de urgência, não houve adaptação do fluxo assistencial, mesmo sendo tecnicamente possível.
A12: Março | B12: "O mês de março representou um retrocesso no desempenho, voltando ao mesmo nível de janeiro. O número absoluto de pacientes no protocolo aumentou, mas a proporção de adesão manteve-se baixa. As auditorias revelaram que, mesmo quando o suplemento era indicado na consulta pré-anestésica, sua prescrição não era concretizada no prontuário eletrônico. Não foram encontrados registros consistentes de horário de administração e avaliação glicêmica prévia, especialmente em pacientes diabéticos. A fragmentação das informações entre os setores de internação, anestesia e centro cirúrgico agrava o cenário, dificultando a rastreabilidade das ações e a responsabilização das falhas."
A14: MÊS | B14: Análise Critica | D14: Plan (Planejar) | G14: Do (Executar/Fazer) | J14: Check (Verificar/Checar) | M14: Act (Agir/Ajustar/Padronizar)
A15: Abril | B15: "Em abril, a adesão ao protocolo atingiu o melhor resultado do semestre, mas ainda está aquém da meta mínima aceitável. Esse leve avanço pode ter sido reflexo de ações educativas realizadas no final de março, mas não foi suficiente para consolidar uma mudança sistêmica. A análise crítica aponta que a ausência de um fluxo assistencial bem definido e automatizado é a principal barreira. Casos auditados indicam que mesmo com consulta pré-anestésica adequada, o suplemento não era prescrito, ou quando prescrito, a administração não acontecia dentro do tempo recomendado, principalmente nos primeiros horários da manhã. Isso reflete falhas na comunicação entre setores e ausência de monitoramento ativo." | D15: Durante o 2º trimestre, o indicador apresentou leve oscilação, com pico de 41% em abril, queda para 38% em maio e manutenção em 40% em junho. Apesar de avanços pontuais, a adesão ao protocolo segue aquém da meta institucional. Principais causas identificadas: Ausência de um fluxo assistencial automatizado entre prescrição, enfermagem e administração. Falta de uniformidade na avaliação pré-anestésica, com prescrições ausentes e orientações insuficientes aos pacientes. Administração fora do tempo recomendado, sobretudo em cirurgias nos primeiros horários da manhã. Baixa rastreabilidade documental, sem registro de horário ou justificativas de não adesão. Inconsistência nas ações educativas para os profissionais envolvidos. Objetivos para o proximo trimestre: Elevar a adesão média para ≥45% até setembro/2025, com padronização do fluxo de execução e monitoramento ativo. | G15: Ações implementadas ou em andamento: Reforço das ações educativas com foco na equipe de enfermagem e anestesia — incluindo revisão dos tempos de administração e benefícios clínicos da abreviação do jejum. Ampliação das auditorias clínicas conjuntas entre anestesia, nutrição e enfermagem, com ênfase em rastreabilidade documental e consistência de prescrição. Discussão com a equipe médica (anestesistas) e nutrição sobre a necessidade de revisão do fluxo de jejum em pacientes do primeiro horario da agenda da manhã, especialmente os internados. Envolvimento do setor de nutrição no acompanhamento pré-operatório de pacientes elegíveis. | J15: O periodo mostrou avanços discretos, porém sem consolidação. O processo ainda depende de iniciativa individual e não está bem institucionalizado especialmente na clareza na aplicação do protocolo em determinado grupos de pacientes ( primeiras cirurgias da manhã, pacientes internados, procedimentos especificos...). Persistem lacunas de integração entre a prescrição do suplemento e a utilização, alem de baixa conformidade nas indicações. Evidências de monitoramento: Média trimestral de adesão: 39,6%. Conformidade nas auditorias: Prescrição: 56% Administração: 51% Registro de horário: 47% Principais falhas identificadas: Falta de prescrição ou prescrição fora do tempo ideal. Recusa do paciente em tomar o suplemento por falta de conhecimento dos beneficios. Inconsistência no registro de administração no PEP dificultando o monitoramento fididigno do indicador. Ausência de responsável designado para checagem diária no bate-mapa cirurgico. | M15: Ações corretivas e padronização propostas: Implantar campo obrigatório no PEP: “Paciente incluído no protocolo de abreviação do jejum / motivo de não adesão”. Definir responsabilidade formal: anestesista como prescritor líder e participação do bate-mapa como metodo de monitorar os pacientes não incluidos no protocolo. Instituir rotina de devolutiva mensal das auditorias, com feedback individualizado aos anestesistas. Ampliar envolvimento da nutrição clínica, atuando na busca ativa de pacientes elegíveis e no acompanhamento das recusas. Meta para o próximo ciclo (3º trimestre): Atingir ≥45% de adesão ao protocolo. Consolidar registro e rastreabilidade no sistema eletrônico. Melhorar a integração entre anestesia, enfermagem e nutrição.
A17: Maio | B17: "Em maio, houve nova queda na adesão. O número de pacientes no protocolo aumentou, mas sem uma resposta proporcional na cobertura com suplemento. Persistem falhas graves, como: Prescrições feitas, mas não administradas; Administrações fora do tempo adequado; Ausência de critérios uniformes na avaliação anestésica. Os registros seguem incompletos e com baixa consistência documental, impossibilitando ações corretivas assertivas e comprometendo a rastreabilidade institucional."
A19: Junho | B19: "Em junho, a taxa de adesão permaneceu abaixo da meta, demonstrando uma estagnação nos avanços obtidos em abril. A principal fragilidade segue sendo a falta de sistematização do protocolo de ponta a ponta, da avaliação inicial à checagem pós-administração. A falta de clareza sobre quem é o responsável final pela prescrição e acompanhamento da administração gera confusão entre equipes e deixa o processo vulnerável. Apesar de alguns profissionais já aplicarem o protocolo com fidelidade, esses casos ainda são exceções, e não uma prática institucionalizada."
A21: MÊS | B21: Análise Critica | D21: Plan (Planejar) | G21: Do (Executar/Fazer) | J21: Check (Verificar/Checar) | M21: Act (Agir/Ajustar/Padronizar)
A22: Julho | B22: O mês de julho manteve baixo desempenho (40%), refletindo ausência de melhoria em relação a junho (40%) e confirmando não conformidade com a meta institucional de >60%. Dos 728 pacientes incluídos no protocolo, apenas 293 receberam o suplemento, o que indica que mais da metade dos pacientes (57%) permaneceram em jejum prolongado. As auditorias clínicas do período evidenciaram média de conformidade do protocolo de jejum e suplementação de 51%, com deficiências em prescrição (52%) e registro (48%). Persistem falhas recorrentes: ausência de prescrição no prontuário, omissão de registro da administração e comunicação ineficiente entre anestesia, paciente e enfermagem. Os registros errados/incompletos no PEP impactam confiabilidade e rastreabilidade dos dados. | D22: Durante o 3º trimestre, manteve-se o desempenho abaixo da meta institucional, com leve oscilação entre 40% e 43%, seguido de queda para 42% em setembro. A adesão ao protocolo manteve-se estável, persistindo as falhas estruturais e operacionais no processo de prescrição, execução e registro do suplemento. Principais causas identificadas: Ausência ou atraso na prescrição médica do suplemento na consulta pré anestesica ou para pacientes internados. Falhas na administração dentro do tempo recomendado, especialmente nas primeiras cirurgias do dia. Registros incompletos ou inconsistentes no prontuário eletrônico. Dificuldade de coleta consolidada do indicador nos painéis institucionais. Falta de clareza nos critérios de inclusão em casos de urgência. Resistência de parte da equipe cirurgica e falhas na comunicação entre anestesia, enfermagem e nutrição. Tempo insuficiente entre internação(gestão de acesso) e administração do suplemento. Objetivos para o ciclo: Elevar a adesão média para ≥50% até o final do próximo trimestre. Consolidar a rastreabilidade dos registros no PEP e nos painéis hospitalares. Revisar e atualizar o protocolo institucional de abreviação do jejum com base nas diretrizes atuais. Uniformizar o fluxo assistencial entre anestesia, centro cirúrgico, internação cirúrgica e nutrição. Implantar cartilha de orientação ao paciente que passa por consulta pré anestesica. | G22: Ações executadas e em andamento: Reunião multiprofissional entre anestesia, centro cirúrgico, unidade de internação cirúrgica e nutrição clínica para revisar fluxos, corrigir falhas e ampliar a adesão. Integração das análises do indicador entre hospital e serviço de anestesia, unificando a base de dados e a leitura de resultados. Atualização do folder informativo para pacientes, incluindo a orientação: “Caso não haja horário definido para cirurgia, ofertar o suplemento X horas antes.” (material em revisão final para envio ao marketing até 22/10). Revisão das diretrizes de referência (Guidelines), mantendo o jejum para sólidos em 6 horas, conforme consenso multiprofissional. Definição de um painel único para controle do indicador e centralização do fechamento dos resultados de jejum externo. Inclusão no histórico do Centro Cirúrgico da pergunta: “Paciente optou por não fazer uso do suplemento?”, visando rastreabilidade da recusa. Revisão dos tempos de tolerância ao uso dos agonistas do receptor de GLP-1, adequando o protocolo às novas evidências clínicas. Nutrição clínica intensificou busca ativa dos pacientes desde a gestão de acesso, avaliando possibilidade de antecipação da chegada para permitir o consumo dentro do tempo seguro. | J22: Resultados quantitativos: Adesão média do trimestre: 41,6% (Julho: 40%, Agosto: 43%, Setembro: 42%). Conformidade média nas auditorias: Prescrição 55% | Administração 49% | Registro 46%. Melhor documentação pré-anestésica (68%), mas falhas persistentes na execução e registro. Resultados qualitativos: A integração entre serviços e setores começou a apresentar melhor articulação de informações. O envolvimento da nutrição clínica ampliou a triagem de pacientes elegíveis, porém o tempo entre admissão e oferta do suplemento ainda é uma limitação operacional relevante. Persistem falhas de registro no PEP e dificuldades de consolidação dos dados no painel institucional, dificultando o monitoramento preciso do indicador. A análise do serviço de anestesia passou a ser integrada ao sistema hospitalar, fortalecendo a governança do processo. | M22: Ações corretivas e preventivas para o próximo ciclo: Formalizar o protocolo revisado, incorporando as diretrizes atualizadas e a padronização do tempo de jejum (6h para sólidos). Implantar o painel único de controle, centralizando o fechamento dos indicadores de jejum e suplementação. Incluir no histórico do PEP e no Centro Cirúrgico o campo obrigatório de registro: “Paciente optou por não fazer uso do suplemento” e o motivo da não adesão. Aprimorar o processo de busca ativa, avaliando estratégias para reduzir o intervalo entre internação e oferta do suplemento. Nutrição seguirá descrevendo o motivo de cada “tempo insuficiente” para análise e correção do indicador interno. Retomar as devolutivas mensais às equipes assistenciais, com foco nas unidades de maior não conformidade. Revisar fluxos e protocolos em conjunto com anestesia e enfermagem, garantindo execução dentro do tempo preconizado. Monitorar e avaliar o impacto das ações implementadas no 4º trimestre, buscando elevar a adesão média para ≥50% .
A24: Agosto | B24: Agosto apresentou pequeno avanço (43%), com 366 pacientes suplementados de um total de 842 incluídos no protocolo. Apesar da melhora marginal, o resultado segue 17 pontos percentuais abaixo da meta mínima. As auditorias indicaram melhor documentação na consulta pré-anestésica (68%), Houve melhora na documentação da consulta pré-anestésica (68%), reflexo das ações e devolutivas iniciadas no trimestre anterior. Apesar disso, persistem falhas na execução e no registro, principalmente em pacientes de urgência com tempo habil para inclusão no protocolo, cuja adesão foi inferior a 45%. A prescrição médica na consulta pré anestesica melhorou marginalmente, mas não houve correspondência na administração prática. As causas predominantes são falta de uniformidade nos critérios de inclusão dos pacientes ( horario da cirurgia, procedimentos cirurgicos, condições clinicas do paciente), A resistência de parte do corpo clínico em aderir ao protocolo e orientar o paciente quanto ao uso tem dificultando a consolidação do processo.
A26: Setembro | B26: Em setembro, observou-se uma leve queda na adesão ao protocolo, atingindo 42%, com 360 pacientes suplementados entre 851 incluídos, o que sinaliza estagnação do avanço obtido em agosto. A análise crítica dos relatórios de segurança confirma a recorrência de falhas de processo, incluindo registros de incidentes relacionados ao Protocolo de Abreviação do Jejum e ausência de documentação adequada. Os achados reforçam que o problema persiste entre a prescrição e a execução do protocolo — ou seja, o suplemento é prescrito, mas não administrado, ou é administrado fora do tempo recomendado. Além disso, permanecem falhas na indicação do suplemento, bem como dificuldades na coleta e consolidação dos dados do indicador por meio dos painéis institucionais do hospital. Persistem também inconsistências nos registros da consulta pré-anestésica e na admissão do paciente no Centro Cirúrgico. Durante o mês de setembro, foi realizada reunião conjunta entre os serviços de anestesia, centro cirúrgico, unidade de internação cirúrgica e nutrição clínica, com o objetivo de ampliar a adesão ao protocolo e corrigir falhas persistentes. Nessa ocasião, foi também integrada à análise do indicador — anteriormente conduzida de forma paralela pelo serviço de anestesia — a avaliação institucional, permitindo uma discussão conjunta dos resultados das auditorias clínicas e das dificuldades enfrentadas pelos serviços na aplicação do protocolo, tanto para pacientes com consulta pré-anestésica agendada, quanto para pacientes internados com tempo hábil de inclusão e aqueles admitidos sem inserção adequada no protocolo ou fora do tempo recomendado.
A28: MÊS | B28: Análise Critica | D28: Plan (Planejar) | G28: Do (Executar/Fazer) | J28: Check (Verificar/Checar) | M28: Act (Agir/Ajustar/Padronizar)
A29: Outubro
A31: Novembro
A33: Dezembro

Sheet Incidencia de PCR até a Alta
A1: INCIDÊNCIA DE PARADA CARDIORRESPIRATÓRIA NO PERÍODO DA INDUÇÃO ATÉ A ALTA ANESTÉSICA | C1: 2025
C2: =C4/C5 -> 0 | D2: =D4/D5 -> 0 | E2: =E4/E5 -> 0 | F2: =F4/F5 -> 0 | G2: =G4/G5 -> 0 | H2: =H4/H5 -> 0 | I2: =I4/I5 -> 0 | J2: =J4/J5 -> 0.00058139535 | K2: =K4/K5 -> 0.00054854635 | O2: =MEDIAN(C2:N2) -> 0
A3: MÊS | C3: Janeiro | D3: Fevereiro | E3: Março | F3: Abril | G3: Maio | H3: Junho | I3: Julho | J3: Agosto | K3: Setembro | L3: Outubro | M3: Novembro | N3: Dezembro | O3: Média anual
A4: Nº de pacientes submetidos a procedimentos sob anestesia/sedação com ocorrência de parada cardiorrespiratória no período da indução até a alta anestésica da SRPA ou transferência para UTI | C4: 0 | D4: 0 | E4: 0 | F4: 0 | G4: 0 | H4: 0 | I4: 0 | J4: 1 | K4: 1 | O4: =+MEDIAN(C4:N4) -> 0
A5: Nº de pacientes submetidos a procedimento sob anestesia/sedação | C5: 1472 | D5: 1535 | E5: 1533 | F5: 1622 | G5: 1607 | H5: 1530 | I5: 1781 | J5: 1720 | K5: 1823 | L5: 0 | M5: 0 | N5: 0 | O5: =MEDIAN(C5:N5) -> 1534
A6: META | C6: Meta zero / ≤1/10.000 anestesias
A7: MÊS | B7: Análise Critica | D7: Plan (Planejar) | G7: Do (Executar/Fazer) | J7: Check (Verificar/Checar) | M7: Act (Agir/Ajustar/Padronizar)
A8: Janeiro | B8: Não houve casos de PCR
A9: Fevereiro | B9: Não houve casos de PCR
A10: Março | B10: Não houve casos de PCR
A11: Abril | B11: Não houve casos de PCR
A12: Maio | B12: Não houve casos de PCR
A13: Junho | B13: Não houve casos de PCR
A14: MÊS | B14: Análise Critica | D14: Plan (Planejar) | G14: Do (Executar/Fazer) | J14: Check (Verificar/Checar) | M14: Act (Agir/Ajustar/Padronizar)
A15: Julho | B15: Não houve casos de PCR (análise de óbito)
A16: Agosto | B16: Resultado: 1 ocorrência / 1.781 anestesias Taxa: 0,00056/10.000 (dentro da meta) Descrição do evento: Durante procedimento de angioplastia complexa (técnica retrógrada por colateral epicárdica), paciente apresentou tamponamento cardíaco com evolução para parada cardiorrespiratória (PCR). A resposta da equipe foi imediata, com drenagem pericárdica de urgência, uso de suporte mecânico (BIA) e drogas vasoativas. Após manobras de reanimação, o paciente evoluiu com retorno da circulação espontânea (RCE) e foi encaminhado à UTI em estabilidade hemodinâmica. Análise crítica: Trata-se de evento adverso grave não evitável, decorrente de complicação mecânica relacionada à técnica do procedimento, e não de falha assistencial. O caso evidencia boa integração entre equipe médica, enfermagem e hemodinâmica, com resposta rápida e protocolos de emergência executados corretamente. A revisão do evento em comitê apontou aderência total aos POPs anestésicos e protocolos de suporte avançado de vida (ACLS). Conclusão: Ocorrência dentro do risco inerente à complexidade do caso. Sem falha técnica identificada. A resposta institucional foi adequada, rápida e segura.
A17: Setembro | B17: 1 ocorrência de PCR / 1.823 anestesias realizadas. Taxa: 0,00055/10.000 anestesias (dentro da meta). Descrição do evento: 1 caso: Paciente do sexo feminino, em estado séptico e instabilidade hemodinâmica grave, submetida à laparotomia de urgência. Durante a indução anestésica, apresentou duas paradas cardiorrespiratórias, revertidas após 1 ciclo de RCP em cada episódio. A paciente foi transferida para UTI, com recuperação hemodinâmica inicial e sem dano neurológico imediato. O evento foi classificado como não evitável, diretamente relacionado à condição clínica crítica da paciente. A resposta da equipe foi imediata e tecnicamente adequada, com atuação coordenada entre anestesia, enfermagem e centro cirúrgico. O caso reforça a importância da estratificação de risco anestésico em emergências, especialmente em pacientes sépticos e hipovolêmicos. Os registros e relatórios de anestesia demonstraram aderência integral ao protocolo institucional de PCR intraoperatória, sem falhas identificadas. Conclusão: Indicador dentro da meta. Evento isolado, não relacionado a falha de processo ou técnica anestésica.
A18: Outubro
A19: Novembro
A20: Dezembro

Sheet % Mudança da Tecnica Anestésica
A1: TAXA DE MUDANÇA DE TÉCNICA ANESTÉSICA | C1: 2025
C2: 0 | D2: 0 | E2: 0 | F2: 0 | G2: 0 | H2: 0 | I2: 0 | J2: 0 | K2: 0.001 | O2: =MEDIAN(C2:N2) -> 0
A3: MÊS | C3: Janeiro | D3: Fevereiro | E3: Março | F3: Abril | G3: Maio | H3: Junho | I3: Julho | J3: Agosto | K3: Setembro | L3: Outubro | M3: Novembro | N3: Dezembro | O3: Média Anual
A4: Nº de pacientes submetidos a procedimentos sob anestesia/sedação que tiveram mudança de técnica anestésica durante período intraoperatório devido a causas relativas a anestesia | C4: 0 | D4: 0 | E4: 0 | F4: 0 | G4: 0 | H4: 0 | I4: 0 | J4: 0 | K4: 1 | O4: =MEDIAN(C4:N4) -> 0
A5: Nº de pacientes submetidos a procedimentos sob anestesia/sedação | C5: 1472 | D5: 1535 | E5: 1533 | F5: 1622 | G5: 1607 | H5: 1530 | I5: 1781 | J5: 1720 | K5: 1823 | L5: 0 | M5: 0 | N5: 0 | O5: =MEDIAN(C5:N5) -> 1534
A6: META | C6: <5%
A7: MÊS | B7: Análise Critica | D7: Plan (Planejar) | G7: Do (Executar/Fazer) | J7: Check (Verificar/Checar) | M7: Act (Agir/Ajustar/Padronizar)
A8: SETEMBRO | B8: O indicador apresentou resultado estável e dentro da meta em todos os meses anteriores (0%), sem registro de outras ocorrências formais. Entretanto, durante a discussão em comitê, foi levantada a possibilidade de subnotificação de falhas anestésicas funcionais nos meses anteriores, uma vez que parte das conversões de técnica — especialmente em bloqueios parciais revertidos rapidamente — pode não ter sido registrada formalmente no sistema AxReg. Além disso, identificou-se dificuldade na busca ativa e rastreabilidade dessas ocorrências, já que nem sempre há correlação direta entre o prontuário anestésico e a notificação de evento adverso. Esse achado reforça a necessidade de fortalecer os mecanismos de vigilância ativa e integração entre os registros de anestesia, auditoria clínica e segurança do paciente. Descrição do Caso – Setembro / 2025 No dia 10/09/2025, durante procedimento ortopédico eletivo, o paciente Gabriel Enriquez Marin Perez apresentou falha de raquianestesia após punção única (L4–L5, agulha Whitacre 27G, líquor claro e refluxo adequado). Após o início da incisão, foi observada ineficácia parcial do bloqueio, com resposta motora e sensibilidade preservadas em um dos dermátomos cirúrgicos. A equipe anestésica reconheceu prontamente a falha e realizou conversão para anestesia geral balanceada com máscara laríngea nº3 e sevoflurano, mantendo estabilidade hemodinâmica e respiratória durante todo o procedimento. Classificação do incidente: Tipo: Evento adverso anestésico-cirúrgico Natureza: Falha funcional de bloqueio raquidiano Consequência: Dano leve e autolimitado (prolongamento do tempo anestésico, sem repercussões clínicas) Causa raiz: Dispersão insuficiente do anestésico local (fator intrínseco / variabilidade individual) | D8: 1- Verificar histórico do indicador e potenciais subnotificações de eventos funcionais (bloqueios parciais não registrados). 2 - Definir plano de ação para fortalecer a rastreabilidade e vigilância ativa dessas ocorrências no centro cirúrgico. | G8: Realizada investigação clínica do caso de falha raquidiana (L4–L5) durante procedimento ortopédico, com conversão imediata para anestesia geral balanceada. A equipe anestésica atuou conforme boas práticas: reconhecimento precoce, comunicação com a equipe cirúrgica, manutenção da estabilidade e registro completo no AxReg. A ocorrência foi discutida em reunião multiprofissional (anestesia, enfermagem e qualidade) para análise técnica e identificação de oportunidades de melhoria. Divulgadas orientações sobre importância do registro de falhas técnicas e funcionais, ainda que sem dano. | J8: Indicador manteve-se dentro da meta institucional, com 0,1% no mês e 0% de média anual. Revisão retrospectiva identificou baixa incidência de notificações, sugerindo possível subnotificação de eventos similares em meses anteriores. Concluiu-se que o evento foi não evitável, decorrente de variação individual na difusão do anestésico local — sem relação com erro técnico. | M8: Instituir busca ativa mensal via AxReg e painéis de anestesia para monitorar conversões não notificadas. Reforçar treinamentos sobre rastreabilidade e registro de eventos anestésicos, incluindo falhas funcionais e bloqueios parciais. Apresentar resultados e aprendizados em reunião trimestral de qualidade e segurança, consolidando cultura de transparência e melhoria contínua. Reavaliar o indicador após 90 dias para medir impacto das ações corretivas e ajustar fluxos se necessário.

Sheet % Incidência Enc. UTI
A1: ANO | C1: 2025
A2: INCIDÊNCIA DE PACIENTES ENCAMINHADOS PARA UTI SEM PLANEJAMENTO PRÉVIO COM INDICAÇÃO DECORRENTE DE EVENTOS ANESTÉSICOS | C2: =C4/C5 -> 0.00071428571 | D2: =D4/D5 -> 0 | E2: =E4/E5 -> 0.00066622252 | F2: =F4/F5 -> 0.00062460962 | G2: =G4/G5 -> 0.0023837902 | H2: =H4/H5 -> 0.0012903226 | I2: =I4/I5 -> 0.0021401819 | J2: =J4/J5 -> 0.0011267606 | K2: =K4/K5 -> 0.0010723861 | O2: =MEDIAN(C2:N2) -> 0.0010723861
A3: MÊS | C3: Janeiro | D3: Fevereiro | E3: Março | F3: Abril | G3: Maio | H3: Junho | I3: Julho | J3: Agosto | K3: Setembro | L3: Outubro | M3: Novembro | N3: Dezembro | O3: Média Anual
A4: Nº de pacientes de cirurgias eletivas sem programação de POI em UTI e que apresentaram evento anestésico necessitando transferência para essa unidade | C4: 1 | D4: 0 | E4: 1 | F4: 1 | G4: 4 | H4: 2 | I4: 4 | J4: 2 | K4: 2 | L4: 0 | M4: 0 | N4: 0 | O4: =MEDIAN(C4:N4) -> 1
A5: Nº de pacientes submetidos a procedimentos eletivos sob anestesia/sedação. | C5: 1400 | D5: 1466 | E5: 1501 | F5: 1601 | G5: 1678 | H5: 1550 | I5: 1869 | J5: 1775 | K5: 1865 | L5: 0 | M5: 0 | N5: 0 | O5: =MEDIAN(C5:N5) -> 1525.5
A6: META | C6: Meta zero / ≤0,3%
A7: MÊS | B7: Análise Critica
A8: JANEIRO | B8: Resultado mensal: 0,1% (1 evento / 1.400 procedimentos) Meta: ≤ 0,3% (meta zero) Situação: Dentro da meta Caso 1 - Ocorreu em paciente do sexo masculino, portador de hipertensão arterial sistêmica e asma, em uso de Enalapril, Diurix, Salbutamol e Fenoterol. Deu entrada no pronto-socorro em 07/01/2025 com quadro compatível com apendicite aguda perfurada e peritonite, sendo submetido à apendicectomia videolaparoscópica com drenagem subfrênica. Durante o pós-operatório imediato, apresentou hipotensão sustentada na SRPA (PAM ≈ 66 mmHg), liberado ao quarto sem reavaliação médica. Na manhã seguinte, evoluiu com sinais de sepse abdominal, sendo necessária ativação do protocolo de sepse, antibioticoterapia de amplo espectro e transferência para UTI para suporte hemodinâmico.A cultura evidenciou E. coli multirresistente, demandando ajuste antimicrobiano (meropeném). Evoluiu com melhora clínica e alta hospitalar em 15/01/2025. Houve falha no reconhecimento precoce da instabilidade hemodinâmica no pós-anestésico imediato, configurando um evento adverso evitável relacionado à transição do cuidado anestésico para o ambiente de internação. fatores contribuintes: Falha de monitoramento e comunicação entre a equipe da SRPA e o plantão no momento da alta do paciente da recuperação anestésica. Ausência de critérios objetivos de estabilidade hemodinâmica para alta da SRPA, especialmente em casos sépticos ou com foco infeccioso estabelecido. Não ADESÃO AO protocolo de reavaliação pós-operatória pelo anestesista antes da alta que poderia ter identificado a deterioração antes da necessidade de transferência à UTI.
A9: FEVEREIRO
A10: MARÇO | B10: Paciente: Edith Mantovani Fontana, 75 anos, portadora de HAS e DM, em uso contínuo de Pregabalina e Duloxetina. Procedimento: Artrodese lombar eletiva sob anestesia geral, duração de 1h30min, sem intercorrências cirúrgicas significativas. No pós-operatório imediato, ainda em sala de recuperação, apresentou episódio de mioclonia após mudança de decúbito (supina) e novas mioclonias após extubação. Evoluiu rapidamente para crise convulsiva tônico-clônica generalizada, necessitando intubação orotraqueal e ventilação mecânica para proteção das vias aéreas, sendo transferida à UTI para suporte intensivo. Os exames complementares (TC de crânio, EEG seriados e exames laboratoriais) descartaram causas estruturais e evidenciaram paroxismos epileptiformes frontais e temporais, compatíveis com encefalopatia medicamentosa e/ou metabólica. O quadro evoluiu com melhora progressiva, permitindo extubação no 3º dia de UTI e alta hospitalar em 24/03/2025, em boas condições clínicas. Evento anestésico-neurológico agudo, de caráter não previsível, porém necessitando de suporte intensivo imediato. Fatores contribuintes identificados: Susceptibilidade neurológica prévia: uso crônico de Pregabalina e Duloxetina, que podem baixar o limiar convulsivo e interagir com anestésicos e analgésicos opioides. Potencial interação medicamentosa: associação entre anestesia geral, agentes sedativos e antidepressivos serotoninérgicos, favorecendo encefalopatia tóxica e crises mioclônicas. Distúrbio metabólico leve no intra e pós-operatório inicial, com hipocalemia (K 2,7) e hipofosfatemia, ambos reconhecidos como precipitantes de atividade epiléptica. Ausência de antecedentes epilépticos conhecidos, configurando evento de caráter idiossincrático, não prevenível no planejamento anestésico habitual.
A11: ABRIL | B11: Resultado mensal: 0,1% (1 evento / 1.601 procedimentos) Meta: ≤ 0,3% (meta zero) Situação: Dentro da meta Paciente: Vitório Ansolin, 71 anos, com histórico de adenocarcinoma gástrico em tratamento quimioterápico paliativo (FOLFOX + Nivolumabe), portador de port-a-cath implantado em 14/02/2025, e múltiplas comorbidades (HAS, DM2, estenose aórtica pós-TAVI, FA paroxística). Em 31/03, foi avaliado por infectologia devido a hiperemia, calor e dor no sítio do port-a-cath direito, associadas à elevação de PCR (236 mg/L) e aumento de creatinina (1,9 mg/dL). O ultrassom mostrou coleção subclávia sugestiva de abscesso peri-cateter, com indicação de retirada do dispositivo. Em 01/04, foi realizada remoção do port-a-cath direito e colocação de novo cateter à esquerda, sob anestesia local e sem sedação. Durante a recuperação anestésica (SRPA), o paciente evoluiu com taquicardia, tremores e agitação psicomotora, seguidos de hipotensão persistente (≈90x60 mmHg) e taquicardia (105 bpm), caracterizando choque séptico pós-procedimento. Foi administrado vasopressor e, diante da instabilidade, realizada transferência imediata para UTI, onde recebeu suporte hemodinâmico, antibioticoterapia de amplo espectro (cefepime + daptomicina) e medidas de controle da infecção. A cultura da ponta do cateter confirmou infecção de corrente sanguínea associada ao port-a-cath (ICSAC). Evoluiu com melhora clínica após terapia intensiva e ajuste antimicrobiano. Infecção pré-existente do port-a-cath com sinais flogísticos evidentes antes da intervenção, mas sem bacteremia confirmada. Paciente oncológico imunossuprimido, neutropênico e com múltiplas comorbidades cardiovasculares, aumentando o risco de descompensação hemodinâmica. Provável liberação bacteriana sistêmica durante a manipulação e retirada do dispositivo infectado, precipitando choque séptico intra/SRPA. Ausência de planejamento prévio para suporte intensivo imediato, apesar do alto risco de instabilidade, o que caracteriza transferência não planejada à UTI. O evento representa uma intercorrência infecciosa grave com descompensação hemodinâmica imediata no pós-procedimento, configurando encaminhamento não planejado à UTI. Embora previsível em termos de risco (dado o contexto séptico e oncológico), o choque séptico instalou-se abruptamente, justificando o acionamento emergencial.
A12: MAIO | B12: O mês de maio apresentou um pico isolado do indicador, atingindo 0,24% (quatro casos em 1.678 procedimentos), resultado ainda dentro da meta institucional (≤0,3%), chama atenção pela concentração de ocorrências em um único período. A análise conjunta dos casos aponta variabilidade clínica e operacional como principal fator contributivo, evidenciando o impacto das situações de fragilidades pontuais no planejamento e triagem pré-operatória. Caso 1- Fernanda Mara Peretti, submetida a histerectomia vaginal, apresentou hipotensão refratária à reposição volêmica na SRPA, mantendo perfusão adequada e exigindo uso transitório de vasopressor. O quadro caracterizou uma vasoplegia anestésica, possivelmente associada ao efeito residual dos agentes anestésicos e ao bloqueio simpático do ato cirúrgico. O encaminhamento à UTI foi necessário para estabilização hemodinâmica, configurando evento anestésico não planejado, parcialmente evitável com aplicação de protocolo de avaliação hemodinâmica antes da alta da SRPA. Caso 2 - , Radamés Pereira, em investigação neurológica por suspeita de Síndrome de Guillain-Barré, sofreu broncoaspiração de conteúdo gástrico durante exame de ressonância magnética sob sedação. O paciente apresentava fatores predisponentes (DRGE, constipação e jejum prolongado), configurando situação de risco aumentado para aspiração. O episódio exigiu transferência imediata à UTI por precaução respiratória, sendo posteriormente confirmado diagnóstico de broncopneumonia aspirativa. Trata-se de evento anestésico fora do centro cirúrgico, considerado parcialmente evitável mediante triagem rigorosa e plano anestésico adequado ao risco. Caso 3 - , Severino da Silva Pereira, foi submetido a artroplastia total de quadril e apresentou hipotensão significativa na SRPA após sangramento intraoperatório moderado, embora já houvesse previsão de leito em UTI no pré-operatório. O encaminhamento acabou ocorrendo de forma tardia, após tentativa de estabilização na recuperação anestésica, o que caracteriza falha de processo e de comunicação entre as equipes quanto ao destino pós-operatório previamente acordado. Ainda que clinicamente controlado, o caso evidencia a necessidade de reforçar o registro formal e o bloqueio administrativo de leitos de UTI previamente programados para cirurgias de grande porte. Caso 4 - Danielle Lemes Fraga, foi submetida a videolaparoscopia de urgência por gravidez ectópica rota com sangramento ativo e grande volume de sangue livre na cavidade abdominal. No pós-anestésico imediato, apresentava taquicardia e sinais de hipovolemia, sendo prontamente encaminhada à UTI para suporte hemodinâmico. Embora o evento tenha origem obstétrica e cirúrgica, foi incluído no numerador do indicador por tratar-se de descompensação clínica detectada na SRPA após anestesia. Trata-se de caso inevitável, relacionado à gravidade da condição de base e não a falha de conduta anestésica. De modo geral, os quatro casos reforçam a importância da padronização dos critérios de alta da SRPA, da triagem anestésica estruturada e da definição clara do destino pós-operatório no checklist cirúrgico. A análise de causa raiz conduzida: Apontou falhas de comunicação intersetorial, heterogeneidade de condutas e deficiência na formalização do planejamento de leitos críticos como fatores contribuintes. Como resposta, foram implantadas ações corretivas voltadas à avaliação dos riscos na consulta/avaliação pré-anestésica, auditoria sistemática dos encaminhamentos não planejados. O resultado de maio é interpretado como pico isolado decorrente de variabilidade clínica e operacional.
A13: JUNHO | B13: O mês de junho apresentou duas ocorrências de encaminhamentos não planejados à UTI por eventos clínicos detectados na Sala de Recuperação Pós-Anestésica (SRPA), mantendo o indicador em 0,13% (2 casos/1.550 procedimentos) — valor dentro da meta institucional (≤0,3%), sem tendência de elevação. Os episódios analisados mantêm o perfil de eventos de baixa gravidade, prontamente reconhecidos e manejados de forma adequada, refletindo um processo assistencial seguro, mas que ainda demanda atenção contínua à vigilância hemodinâmica e avaliação clínica precoce na SRPA. Caso 1 - Ires Salete Wesoloski, 62 anos, submetida a mamoplastia redutora associada a lipoaspiração e dermolipectomia abdominal. O ato anestésico transcorrera sem intercorrências, porém, no pós-operatório imediato, a paciente apresentou hipotensão postural persistente, refratária à infusão de 2.500 ml de cristaloide, o que motivou sua transferência da SRPA para a UTI. A paciente possuía hipertensão arterial sistêmica e trombofilia familiar (Fator V de Leiden), condições predisponentes a labilidade hemodinâmica e risco tromboembólico. Na avaliação da UTI, encontrava-se lúcida, sem sinais de choque ou sangramento ativo, com perfusão periférica preservada e hemodinamicamente compensada após suporte com vasopressor leve. O caso caracteriza evento anestésico de natureza hemodinâmica, não grave, possivelmente relacionado à vasoplegia induzida por anestésicos, volume aspirado e redistribuição volêmica. Apesar do encaminhamento não planejado, houve resolução completa em menos de 24 horas, com alta precoce da terapia intensiva e sem complicações secundárias. Caso 2 - Daiane Vanessa Riquetta Alberici, 36 anos, foi admitida na SRPA após apendicectomia videolaparoscópica por apendicite aguda supurada com peritonite, com quadro clínico de cinco dias de evolução prévia. O procedimento ocorreu sem instabilidade intraoperatória, mas, pela gravidade do processo infeccioso e risco de sepse abdominal, foi decidido, em consenso entre anestesiologia e cirurgia, encaminhamento imediato à UTI para vigilância intensiva e controle clínico pós-operatório. A paciente manteve-se hemodinamicamente estável e sem necessidade de drogas vasoativas, evoluindo com boa resposta ao tratamento antimicrobiano e alta da UTI no 5º dia pós-operatório. Embora o encaminhamento tenha sido planejado durante o intraoperatório, o caso foi incluído no indicador por ter ocorrido a partir da SRPA, sem reserva de leito previamente registrada — o que o caracteriza falha na formalização do planejamento do destino pós-cirúrgico, e não de falha técnica anestésica. De modo geral, as ocorrências do mês de junho demonstram baixa gravidade clínica e ausência de desfechos adversos relevantes, sendo ambas relacionadas a instabilidades hemodinâmicas e condições clínicas prévias, mais do que a intercorrências anestésicas propriamente ditas. A causa raiz apontou fatores contribuintes ligados à ausência de padronização na definição pré-operatória do destino pós-anestésico, à falha na comunicação entre anestesia, SRPA e equipe cirúrgica, e à variação de conduta no reconhecimento da necessidade de UTI precoce, especialmente em pacientes de risco intermediário. Foram reforçadas as rotinas de avaliação pré-anestésica com estratificação de risco hemodinâmico, a formalização do campo “Destino Pós-Operatório” no prontuário eletrônico. Também foi discutida com as equipes do CC confirmando o planejamento antecipado de leito em pacientes com risco ASA II–III submetidos a procedimentos de médio ou grande porte, de forma a evitar decisões tardias e transferências não programadas. Em síntese, o comportamento do indicador em junho reflete estabilidade e efetividade das medidas implantadas nos meses anteriores, com manutenção dentro da meta e encaminhamentos adequados do ponto de vista assistencial, porém ainda com oportunidade de melhoria na comunicação e no planejamento intersetorial. O cenário é compatível com controle do processo anestésico e amadurecimento institucional das práticas de gestão de risco perioperatório.
A14: JULHO | B14: O mês de julho apresentou quatro casos de encaminhamento não programado à UTI decorrentes de eventos detectados na Sala de Recuperação Pós-Anestésica (SRPA), com incidência de 0,21% (4 casos / 1.869 procedimentos), valor dentro da meta institucional (≤0,3%), embora com leve elevação em relação aos dois meses anteriores. O perfil das ocorrências demonstra características multifatoriais e recorrentes, envolvendo falhas de planejamento pré-operatório, instabilidade hemodinâmica pós-anestésica e decisões clínicas corretas, porém reativas, em vez de preventivas. Caso 1 - Hilário José Mallmann, 75 anos, submetido a artroplastia total de joelho direito. O evento foi caracterizado por falha processual: o paciente possuía recomendação expressa de vigilância intensiva pós-operatória, com reserva de leito em UTI previamente validada, conforme parecer cardiológico e plano anestésico. Contudo, foi inadvertidamente encaminhado à SRPA. Durante a recuperação, apresentou hipotensão leve e sinais de hipoperfusão, o que levou à transferência emergencial para a UTI, corrigindo o erro de fluxo. A análise de causa raiz identificou ausência de conferência formal do destino cirúrgico no checklist de saída da sala, além de lacuna de comunicação entre as equipes de anestesia, cirurgia e enfermagem. O evento é classificado como evitável, com dano leve e temporário, evidenciando necessidade de aprimorar a verificação cruzada do destino conforme plano anestésico. Caso 2 - Marliezer do Nascimento, 29 anos, foi registrado após dermolipectomia com plicatura de reto e lipoaspiração de alto volume (4–4,5 L) sob anestesia geral. Na SRPA, o paciente apresentou hipotensão sustentada, hipocoramento e débito sanguinolento elevado em dreno (≈550 mL), necessitando de reposição volêmica, uso intermitente de vasopressores e transfusão de hemácias (CHAD). A transferência para a UTI foi indicada por instabilidade recorrente e anemia aguda. A investigação apontou que o caso era parcialmente evitável, pois faltou planejamento prévio compatível com cirurgia de grande porte, sem reserva antecipada de sangue ou leito crítico. O manejo clínico foi adequado e a resposta da equipe foi rápida, mas o episódio revelou falha na estratificação de risco e porte cirúrgico em cirurgias plásticas extensas. Caso 3 - Atendimento 2416982 Paciente submetido a cirurgia abdominal de médio porte, que evoluiu na SRPA com hipotensão transitória associada a náusea e sonolência, sem intercorrências intraoperatórias relevantes. A decisão de encaminhamento à UTI foi motivada pela associação de instabilidade hemodinâmica com perfil clínico de risco moderado. O episódio foi classificado como clínico e de gravidade leve, com desfecho favorável após observação intensiva por 24 horas. A análise destacou a boa resposta assistencial imediata, mas também falha no protocolo padronizado de alta da SRPA com critérios objetivos de estabilidade . Caso 4 - (Atendimento 2544650) envolveu paciente no pós-operatório de colecistectomia videolaparoscópica, que evoluiu com bradipneia e hipoxemia durante a recuperação anestésica. Apesar de a anestesia e o ato cirúrgico terem transcorrido sem intercorrências, a paciente apresentou depressão respiratória secundária a efeito residual de opioide e sedação, sendo instituídas medidas de suporte ventilatório e reversão farmacológica, seguidas de encaminhamento à UTI para monitorização contínua. O evento foi considerado não grave e completamente reversível, configurando falha relacionada à variabilidade de resposta farmacológica individual e necessidade de vigilância prolongada na SRPA, mais do que falha técnica anestésica. De forma global, os casos de julho evidenciam : 1- Fragilidade na execuçãoo e validação do planejamento pré-operatório (caso Hilário e Marliezer); 2 - Variabilidade clínica e resposta fisiológica pós-anestésica, que demandaram observação intensiva. A análise demonstra que a resposta clínica foi oportuna e segura, evitando evolução para desfechos adversos, mas as barreiras preventivas a montante ainda falham — especialmente no planejamento de destino, reserva de leitos e classificação de porte anestésico. A cultura de segurança mostrou-se presente nas respostas rápidas da SRPA e na comunicação com a UTI, porém ainda reativa, e não preditiva.
A15: AGOSTO | B15: O mês de agosto apresentou dois casos de encaminhamentos não programados à UTI, resultando em índice de 0,10% (2 casos / 1.915 procedimentos) — dentro da meta institucional (≤0,3%), mantendo a estabilidade do indicador e confirmando o controle do processo assistencial. Ambos os eventos decorreram de intercorrências clínicas reconhecidas e manejadas prontamente na SRPA, com desfechos favoráveis, embora em um deles tenha sido identificado atraso na ativação de protocolo e latência na transferência. Caso 1 - Fabiana Zamodzki, 42 anos, submetida a cesariana gemelar (DIDI) , que evoluiu no pós-operatório imediato com sangramento vaginal volumoso e atonia uterina, progredindo para choque hemorrágico grave. Na SRPA, foram instituídas medidas iniciais de suporte — oxigenoterapia, hidratação vigorosa, uterotônicos e massagem uterina —, porém sem resposta sustentada. Após queda progressiva da pressão arterial e sinais de hipoperfusão, iniciou-se noradrenalina em bomba de infusão e solicitou-se transferência à UTI. A paciente necessitou de histerectomia puerperal de urgência e, no dia seguinte, laparotomia exploradora com ooforectomia esquerda por hemoperitônio residual, além de politransfusão (CHAD, PFC, plaquetas, crioprecipitado). O evento foi classificado como grave, porém não evitável, decorrente de hemorragia obstétrica por atonia uterina refratária, em paciente de alto risco obstétrico (trombofilia, pré-eclâmpsia, gestação gemelar e uso prévio de anticoagulante) A análise de causa raiz evidenciou atraso na ativação formal do Protocolo de Hemorragia Obstétrica e do MTP (Massive Transfusion Protocol), bem como latência na comunicação entre obstetrícia, anestesia, UTI e hemoterapia. O reconhecimento inicial foi precoce, mas o escalonamento terapêutico foi reativo, o que retardou a transferência e a reposição hemoderivada. Apesar disso, a resposta assistencial na fase crítica foi efetiva, e o desfecho clínico foi favorável. As principais oportunidades de melhoria concentram-se em tempo-resposta e integração multiprofissional em emergências obstétricas. Caso 2 - Delmar Zemiani, 47 anos, submetido a artrodese lombossacra por estenose congênita do canal vertebral. Durante fisioterapia respiratória na SRPA, apresentou hipotensão (PA 70x54 mmHg), sudorese e dessaturação leve, mantendo-se consciente e orientado. Após avaliação do anestesiologista, foi iniciado suporte com noradrenalina (4 mL/h) e solicitada vaga em UTI semi-intensiva para observação. Os exames revelaram hipocalcemia leve e lactato discretamente elevado (3,2 mmol/L), sem sinais de isquemia. O evento foi classificado como leve e transitório, sem dano permanente, decorrente de resposta fisiológica individual ao esforço respiratório e suspensão recente de anti-hipertensivo, sem falha técnica ou processual. A análise destacou a importância da checagem hemodinâmica antes da mobilização e a revisão do manejo de anti-hipertensivos no pré e pós-operatório, especialmente em pacientes sob anestesia geral de médio porte. Trata-se de evento não evitável, com gestão clínica exemplar e sem repercussões duradouras. De forma global, os dois casos de agosto demonstram nível elevado de resposta assistencial e segurança no manejo das intercorrências anestésicas, com rápida intervenção e integração multiprofissional, ainda que com necessidade de aprimorar a tempestividade em emergências obstétricas. O comportamento do indicador reforça a efetividade das medidas corretivas implementadas nos meses anteriores, consolidando a estabilidade e a previsibilidade do processo anestésico. Como ações corretivas e preventivas, foram determinadas: Reforço da via rápida UTI para emergências obstétricas e hemorragias graves; Revisão do tempo de ativação do Protocolo de Hemorragia Obstétrica, com simulações multiprofissionais;
A16: SETEMBRO | B16: O mês de setembro apresentou duas ocorrências de encaminhamento não programado à UTI, resultando em incidência de 0,11% (2 casos / 1.865 procedimentos) — valor dentro da meta institucional (≤0,3%), mantendo a estabilidade do indicador. Os casos, embora distintos em natureza clínica, reforçam dois pontos estruturais do processo anestésico: planejamento perioperatório insuficiente em paciente de alto risco e reação rápida e eficaz diante de complicação clínica imprevisível. Caso 1 - Milton Lunardi, 92 anos, submetido a laminectomia torácica com implante de eletrodos para neuromodulação, evoluiu na SRPA com hipotensão persistente (PA 69/42 mmHg) e bradicardia sinusal (52–61 bpm), sem evidências de sangramento ou hipoxemia. Apesar da adequada condução anestésica e extubação sem intercorrências, o paciente apresentou vasoplegia pós-anestésica refratária à reposição volêmica, necessitando de suporte com droga vasoativa (noradrenalina em baixa dose) e encaminhamento imediato à UTI. A investigação revelou perfil clínico de alto risco (ASA III–IV) com múltiplas comorbidades — insuficiência cardíaca com fração de ejeção preservada, fibrilação atrial, diabetes, doença de Parkinson e uso de diurético, antiarrítmico e inibidor de SGLT2 — fatores predisponentes à instabilidade hemodinâmica e disautonomia perioperatória. A análise classificou o evento como potencialmente evitável, uma vez que não houve reserva de leito de UTI previamente, apesar do risco clínico claramente identificado na avaliação pré-anestésica. A falha principal ocorreu no planejamento perioperatório, não na execução técnica ou resposta assistencial. A equipe de anestesia e SRPA respondeu prontamente, mitigando o dano, e o paciente evoluiu com melhora hemodinâmica e alta da UTI em 48 horas, sem sequelas. As recomendações derivadas incluem reforçar a obrigatoriedade de definição do destino pós-operatório na avaliação pré-anestésica e formalizar o critério de reserva antecipada de leito para pacientes ASA III/IV ou com risco cardiovascular elevado. Caso 2 - Guilherme de Rezende Dalul, 40 anos, submetido a tireoidectomia total sem intercorrências cirúrgicas, que apresentou dispneia, estridor e disfonia durante a recuperação anestésica. A fibronasolaringoscopia demonstrou paralisia bilateral de pregas vocais em posição paramediana, complicação conhecida e rara do procedimento. O paciente manteve saturação adequada (96–99%) sob oxigenoterapia e não necessitou de intubação, mas, diante do risco de deterioração respiratória, foi encaminhado preventivamente à UTI para vigilância intensiva, permanecendo em observação por menos de 24 horas e obtendo recuperação completa. O evento foi classificado como não evitável, decorrente de complicação cirúrgica previsível e inerente ao procedimento, sem falha de processo anestésico ou de comunicação. As equipes de anestesia, cirurgia, otorrinolaringologia e enfermagem atuaram de forma coordenada. A transferência precoce à UTI foi medida preventiva adequada, demonstrando maturidade da linha de cuidado cirúrgico e efetividade das barreiras assistenciais. Os casos de setembro refletem a necessidade de reforçar o planejamento antecipado, especialmente em pacientes idosos e com comorbidades múltiplas. O comportamento do indicador mantém tendência estável, dentro da meta, com predominância de eventos clínicos leves a moderados, totalmente resolvidos. Como ações corretivas e preventivas, foram definidas: Revisão do formulário de avaliação pré-anestésica, com campo obrigatório para definição do destino pós-operatório; Integração do protocolo de estratificação de risco perioperatório aos fluxos de agendamento cirúrgico;
A17: OUTUBRO
A18: NOVEMBRO
A19: DEZEMBRO

Sheet % Efet. no controle glicemico
A1: ANO | C1: 2025
A2: EFETIVIDADE DO PROTOCOLO DE CONTROLE GLICÊMICO NO PERÍODO PERIOPERATÓRIO | C2: 0.74 | D2: 0.76 | E2: 0.78 | F2: 0.72 | G2: 0.8 | H2: 0.77 | I2: 0.91 | J2: =J4/J5 -> 0.83878241 | K2: =K4/K5 -> 0.82442748 | O2: =MEDIAN(C2:N2) -> 0.78
A3: MÊS | C3: Janeiro | D3: Fevereiro | E3: Março | F3: Abril | G3: Maio | H3: Junho | I3: Julho | J3: Agosto | K3: Setembro | L3: Outubro | M3: Novembro | N3: Dezembro | O3: Média Anual
A4: Nº de pacientes submetidos a procedimento sob anestesia com a participação do anestesiologista elegíveis ao protocolo de controle glicêmico mantidos com níveis glicêmicos dentro do padronizado | C4: 535 | D4: 619 | E4: 662 | F4: 688 | G4: 764 | H4: 717 | I4: 740 | J4: 744 | K4: 756 | L4: 0 | M4: 0 | N4: 0 | O4: =MEDIAN(C4:N4) -> 675
A5: Nº de pacientes submetidos a procedimento sob anestesia com a participação do anestesiologista elegíveis ao protocolo de controle glicêmico | C5: 726 | D5: 818 | E5: 848 | F5: 949 | G5: 951 | H5: 936 | I5: 880 | J5: 887 | K5: 917 | L5: 0 | M5: 0 | N5: 0 | O5: =MEDIAN(C5:N5) -> 864
A6: META | C6: >90%
A7: MÊS | B7: Análise Critica | D7: Plan (Planejar) | G7: Do (Executar/Fazer) | J7: Check (Verificar/Checar) | M7: Act (Agir/Ajustar/Padronizar)
A8: JANEIRO | B8: No mês de janeiro, o indicador de efetividade do protocolo de controle glicêmico alcançou 74%, abaixo da meta institucional de ≥90%, entre 726 pacientes elegíveis, dos quais 535 mantiveram níveis glicêmicos dentro do padrão. O desempenho evidencia fragilidades relacionadas sobretudo ao monitoramento e ao registro das glicemias no período perioperatório. Entre os pacientes avaliados, 20 apresentaram hipoglicemia (<70 mg/dL) no pré-operatório, e 1 manteve-se hipoglicêmico no pós-operatório, mostrando falha pontual de vigilância e necessidade de ajustes na rotina de rechecagem. Já 14 pacientes apresentaram hiperglicemia (>180 mg/dL) no pré-operatório; 11 evoluíram para normoglicemia, mas 2 permaneceram com valores acima de 207 mg/dL após o procedimento, indicando falhas no manejo intraoperatório e na correção farmacológica. O dado mais crítico do mês foi a ausência de monitoramento em 157 pacientes, comprometendo tanto a avaliação real da efetividade quanto a segurança assistencial, já que impede a identificação precoce de descontrole glicêmico. Esse volume de casos sem aferição sugere uma lacuna sistêmica, e não um evento isolado, interferindo diretamente na confiabilidade do indicador. Assim, janeiro demonstra que o resultado abaixo da meta não se deve predominantemente a falhas terapêuticas, mas sim a inconsistências na execução, adesão e rastreabilidade do protocolo, uma vez que os casos de hipo e hiperglicemia foram pontuais e, em sua maioria, bem conduzidos. Contudo, a grande proporção de pacientes sem monitoramento revela baixa adesão institucional e fragilidade de governança clínica no início do ciclo. | D8: A analise do periodo revelou que a principal causa de não conformidade esteve associada à baixa adesão operacional ao monitoramento glicêmico, evidenciada pela ausência de coletas em uma proporção significativa dos pacientes elegíveis e por falhas repetidas na rechecagem pós-intervenção. Além disso, identificou-se dificuldade na coleta, registro e consolidação dos dados, o que limita a precisão do indicador e compromete as ações de melhoria contínua. Outro ponto crítico foi a estagnação do protocolo, que se manteve sem revisões estruturais, gerando lacunas entre a teoria proposta e a realidade do fluxo clínico-assistencial. Como resposta, definiu-se a necessidade de revisão institucional do Protocolo de Controle Glicêmico Perioperatório, em conjunto com a equipe assistencial e o time de anestesia, buscando atualizar critérios, metas, rotinas de monitorização e estratégias de reavaliação obrigatória. Para isso, o hospital estabeleceu a integração com a endocrinologia, culminando no evento "Atualização PRO Manejo de Hiperglicemia e Hipoglicemia em Pacientes Não Críticos", a ser conduzido pela Dra. Vanessa Tavarone, Médica Endocrinologista. O treinamento, voltado para anestesistas, hospitalistas, equipes de enfermagem do fluxo cirúrgico e unidades clínicas, farmacêuticos e nutricionistas, buscou reforçar definições, metas glicêmicas, diagnósticos, protocolos terapêuticos, manejo de situações especiais e fluxos de alta hospitalar. A metodologia híbrida, com duração de 1 hora. | G8: Durante o 1º semestre, implementou-se um plano preliminar de contenção voltado a: reforçar, por meio das coordenações assistenciais, a necessidade de coleta obrigatória das glicemias pré e pós-operatórias; reforçar a comunicação entre centro cirúrgico, anestesia e recuperação para garantir reavaliação após qualquer intervenção glicêmica; iniciar auditorias amostrais semanais para identificar falhas de registro; revisar pontos críticos do fluxo de atendimento para mapear causas de não monitoramento. Em paralelo, avançou-se na construção do conteúdo institucional que será apresentado no treinamento de setembro, com alinhamento entre endocrinologia, anestesia e gestão hospitalar para padronizar condutas em hipoglicemia, hiperglicemia e manejo de pacientes em situações especiais (insuficiência renal, nutrição enteral/parenteral, corticoterapia, cuidados paliativos). | J8: A análise consolidada de janeiro a junho mostrou que os esforços iniciais de reforço operacional resultaram em melhoras discretas, embora insuficientes para alterar significativamente a trajetória do indicador. Houve leve elevação do desempenho entre abril (72%) e maio (80%), mas junho voltou a apresentar limitação na execução plena do protocolo, com manutenção de percentual elevado de pacientes sem avaliação glicêmica (17,7%). A ausência de mudança estrutural reforçou a necessidade de revisão mais profunda do protocolo e de capacitação formal das equipes. O monitoramento demonstrou que a equipe tem competência técnica para corrigir hipoglicemias e hiperglicemias quando identificadas, mas que as falhas residem essencialmente na detecção, na reavaliação e na documentação, o que reafirma a necessidade de uma intervenção educativa e processual mais robusta. | M8: Com base na avaliação do semestre, a instituição avançará para a fase de padronização e correção estruturada, implementando: revisão completa do protocolo, incorporando critérios mais objetivos de monitorização, metas mais claras e fluxos obrigatórios de rechecagem; Sensibilizações com as equipes reforçando a coleta de glicemias como pré-requisito para avanço do atendimento perioperatório; auditorias sistemáticas, com devolutiva direta às equipes, especialmente para os casos sem monitoramento e falhas na reavaliação; treinamento multiprofissional conduzido pela Dra. Vanessa Tavarone em setembro, reforçando diagnóstico, metas, condutas terapêuticas e atuação integrada; padronização de práticas entre anestesia, enfermagem e equipes clínicas, alinhando o cuidado e fortalecendo a cultura de segurança; monitoramento mensal com análise crítica estruturada, avaliando os impactos pós-treinamento e ajustes necessários.
A9: FEVEREIRO | B9: Em fevereiro, o indicador de efetividade do protocolo de controle glicêmico alcançou 76%, permanecendo abaixo da meta institucional de ≥90%, embora represente leve melhora em relação a janeiro. Dos 818 pacientes elegíveis, 619 mantiveram níveis glicêmicos dentro do padrão, evidenciando progressão gradual na adesão, mas ainda com falhas importantes de monitoramento e registro. Ao analisar os dados clínicos, 22 pacientes apresentaram hipoglicemia pré-operatória (<70 mg/dL), sendo que 2 permaneceram hipoglicêmicos no pós-operatório, revelando falhas na reavaliação e no cumprimento integral das etapas de correção. No grupo com hiperglicemia pré-operatória, 12 pacientes tiveram valores acima de 180 mg/dL, dos quais 7 foram adequadamente corrigidos, enquanto 3 mantiveram índices acima de 209 mg/dL, sugerindo inconsistências no manejo intraoperatório e na efetividade das intervenções. A principal fragilidade do mês, contudo, foi a ausência de monitoramento em 165 pacientes, representando 20% dos elegíveis, o que repete o padrão crítico observado em janeiro. Essa falta de registro compromete a avaliação real do indicador e evidencia uma falha estrutural no processo, associada à integração insuficiente entre enfermagem, anestesiologia e recuperação anestésica, bem como a lacunas na utilização de checklists e sistemas eletrônicos. Embora fevereiro demonstre evolução e capacidade técnica adequada para corrigir hipo e hiperglicemias identificadas, a inconsistência operacional ainda limita o avanço para níveis de desempenho mais elevados. Consolidar o uso de ferramentas de monitoramento obrigatório, intensificar auditorias e reforçar o feedback às equipes serão medidas essenciais para transformar essa tendência de melhora em um avanço sustentável ao longo dos próximos meses.
A10: MARÇO | B10: No mês de março, o indicador de efetividade do protocolo de controle glicêmico atingiu 78%, mantendo leve crescimento, porém ainda distante da meta de ≥90%. Dos 949 pacientes incluídos, 163 (17,2%) não foram avaliados em nenhum momento, mostrando uma lacuna importante no monitoramento e comprometendo a confiabilidade do indicador. Entre os pacientes avaliados no pré-operatório, 52 apresentaram hipoglicemia (<70 mg/dL), e 5 permaneceram hipoglicêmicos no pós-operatório, indicando falhas de vigilância e necessidade de ajustes nos fluxos de correção e rechecagem. Também no pré-operatório, 14 pacientes apresentaram hiperglicemia (184–267 mg/dL); 12 foram corrigidos, enquanto 2 não tiveram reavaliação pós-operatória, revelando inconsistências no fechamento do ciclo assistencial. Entre os 718 pacientes normoglicêmicos, 27 apresentaram hipoglicemia pós-operatória e 5 evoluíram com hiperglicemia (183–198 mg/dL), sugerindo possíveis falhas de manejo intra e pós-cirúrgico. Considerando apenas os 786 pacientes avaliados, 688 permaneceram estáveis durante todo o período perioperatório, enquanto 98 apresentaram algum grau de descontrole, reforçando a necessidade de maior integração entre as equipes. Assim, março evidencia progresso clínico e maior consolidação do protocolo entre os pacientes monitorados, mas a taxa de 17,2% de não monitoramento permanece crítica. O avanço rumo à meta de 90% depende de fortalecimento da governança do protocolo, melhoria dos fluxos de reavaliação e adoção de mecanismos obrigatórios de registro, permitindo que a evolução positiva observada se consolide nos trimestres seguintes.
A11: ABRIL | B11: No mês de abril, o indicador de efetividade do protocolo de controle glicêmico atingiu 72%, ficando novamente abaixo da meta de ≥90% e representando uma queda em relação a março. Dos 949 pacientes incluídos, 163 (17,2%) não foram avaliados em nenhum momento do período perioperatório, indicando falha relevante no monitoramento e refletindo fragilidade operacional e de cultura de segurança. Entre os pacientes avaliados no pré-operatório, 52 apresentaram hipoglicemia (<70 mg/dL), sendo que 5 permaneceram hipoglicêmicos no pós-operatório, revelando falhas de reavaliação e provável ausência de protocolos padronizados ou de vigilância adequada na transição para a recuperação anestésica. Quanto à hiperglicemia, 14 pacientes apresentaram valores acima de 180 mg/dL (184–267 mg/dL) no pré-operatório; 12 foram corrigidos, mas 2 não tiveram rechecagem, o que compromete a validação da correção e reforça falhas no ciclo de monitoramento. Entre os 718 pacientes normoglicêmicos, 27 evoluíram com hipoglicemia pós-operatória e 5 com hiperglicemia (183–198 mg/dL), indicando necessidade de revisão do manejo intraoperatório, principalmente no uso de insulina, controle de jejum e infusões intravenosas. Abril apresentou regressão no desempenho, com persistência de lacunas na documentação, na reavaliação pós-intervenção e no controle glicêmico, apesar da condução terapêutica ser eficaz para a maioria dos pacientes avaliados. O cenário reforça a urgência de retomar a padronização do processo, assegurar aferição documentada nos três momentos críticos, implementar verificações eletrônicas obrigatórias e fortalecer a governança clínica. Esses ajustes são essenciais para corrigir a queda observada e recolocar o indicador no caminho da meta institucional.
A12: MAIO | B12: No mês de maio, o indicador de efetividade do protocolo de controle glicêmico alcançou 80%, representando recuperação significativa em relação a abril e aproximando-se da meta institucional de ≥90%. Apesar do avanço, 137 pacientes ainda não tiveram qualquer registro de avaliação glicêmica, revelando que persistem lacunas importantes na rastreabilidade e na consolidação do processo de monitoramento. Entre os pacientes avaliados, 48 apresentaram hipoglicemia (<70 mg/dL) no pré-operatório; 4 permaneceram hipoglicêmicos no pós-operatório e 7 não foram reavaliados, evidenciando falhas na rechecagem e na execução completa do protocolo. Em relação à hiperglicemia, 7 pacientes apresentaram valores >180 mg/dL na primeira coleta, dos quais 2 permaneceram hiperglicêmicos no pós-operatório, enquanto os demais foram adequadamente corrigidos. Esses dados mostram melhora no manejo intraoperatório, mas reforçam a necessidade de protocolos mais rígidos de reavaliação, sobretudo em pacientes diabéticos ou com maior risco metabólico. O resultado de maio, com aumento da efetividade e redução dos casos de descontrole persistente, indica impacto positivo das ações corretivas adotadas anteriormente, refletindo maior engajamento das equipes e melhor padronização do processo. Contudo, o número ainda elevado de pacientes sem avaliação glicêmica demonstra que o protocolo não está totalmente incorporado à rotina assistencial e que a ausência de monitoramento pode mascarar desvios clínicos relevantes. Assim, o desafio passa a ser manter o desempenho ascendente, eliminar falhas de monitoramento e assegurar que 100% dos pacientes elegíveis sejam avaliados em todas as etapas do perioperatório. A consolidação desse avanço dependerá de auditorias contínuas, integração entre as equipes e fortalecimento da cultura de segurança assistencial.
A13: JUNHO | B13: No mês de junho, o indicador de efetividade do protocolo de controle glicêmico atingiu 77%, mantendo estabilidade em relação a maio, porém ainda distante da meta de ≥90%. Entre os 936 pacientes incluídos, 166 (17,7%) não tiveram nenhum registro de avaliação glicêmica, demonstrando uma lacuna persistente no monitoramento e comprometendo a rastreabilidade do cuidado. Dos 770 pacientes avaliados, 12 apresentaram hiperglicemia (>180 mg/dL) no pré-operatório; 5 não foram reavaliados, 3 permaneceram hiperglicêmicos no pós-operatório e apenas 4 evoluíram para normoglicemia, revelando falhas na continuidade do controle e baixa adesão à rechecagem obrigatória. Em relação à hipoglicemia, 62 pacientes apresentaram valores <70 mg/dL; entre eles, 24 não foram reavaliados, 7 mantiveram-se hipoglicêmicos no pós-operatório e 31 normalizaram os níveis, evidenciando que, embora o protocolo seja eficaz quando aplicado integralmente, ainda enfrenta inconsistências no monitoramento sequencial. Entre os 711 pacientes normoglicêmicos, 29 (4,1%) apresentaram alterações glicêmicas no pós-operatório, indicando episódios de descompensação possivelmente relacionados a jejum prolongado, uso de insulina sem reavaliação, soluções intravenosas inadequadas ou estresse cirúrgico. No conjunto, junho demonstra capacidade clínica sólida na correção dos distúrbios identificados, mas revela fragilidade organizacional pela elevada taxa de pacientes não monitorados e pela falta de padronização no processo de reavaliação. O desempenho do mês caracteriza uma estagnação da curva de melhoria, indicando que o avanço técnico não tem sido acompanhado por evolução operacional. Para aproximar-se da meta de 90%, torna-se essencial fortalecer mecanismos de monitoramento obrigatório, reduzir omissões de registro e garantir que toda intervenção glicêmica seja acompanhada de nova aferição documentada, permitindo transformar o desempenho pontual em um processo assistencial seguro e consistente ao longo do tempo.
A14: MÊS | B14: Análise Critica | D14: Plan (Planejar) | G14: Do (Executar/Fazer) | J14: Check (Verificar/Checar) | M14: Act (Agir/Ajustar/Padronizar)
A15: JULHO | B15: No mês de julho, entre 880 pacientes incluídos no protocolo, observou-se uma efetividade de 91%, resultado impulsionado pelos 740 pacientes que mantiveram controle glicêmico adequado durante o período perioperatório. Foram excluídas 126 crianças até 13 anos, conforme critério do indicador. Entre os avaliados, 70 pacientes apresentaram hipoglicemia (<70 mg/dL) na primeira coleta; destes, 8 permaneceram com glicemias entre 59 e 70 mg/dL no pós-operatório, 24 não foram reavaliados e 35 evoluíram para valores entre 71 e 158 mg/dL após intervenção. Além disso, 6 pacientes apresentaram hiperglicemia (>180 mg/dL) no pré-operatório e não foram reavaliados no pós-operatório. Apesar da melhora expressiva na efetividade, ainda persistem dificuldades na coleta e organização dos dados do indicador | D15: Apesar de julho ter atingido 91% de efetividade, agosto e setembro demonstraram perda progressiva de consistência operacional, com quedas para 84% e 82%, respectivamente. Persistiram fragilidades estruturais, como pacientes sem avaliação glicêmica documentada — 24% em julho (considerando não reavaliados em episódios críticos), 56 casos não monitorados em agosto e 44 em setembro — além de falhas recorrentes de rechecagem nos pacientes com glicemias <70 mg/dL ou >180 mg/dL. Esses dados expõem uma clara estagnação do processo e revelam que as melhorias pontuais não se converteram em maturidade sistêmica do protocolo. o plano para o próximo ciclo deve se concentrar em três pilares centrais: consolidar a implementação da versão atualizada do protocolo publicada em agosto, garantir confiabilidade na coleta e registro das aferições glicêmicas, e reforçar a capacitação técnica das equipes envolvidas no fluxo cirúrgico e clínico. As metas incluem elevar a efetividade para níveis superiores a 90%, reduzir a zero o número de pacientes elegíveis sem aferição glicêmica e assegurar os casos de hipo ou hiperglicemia passem por rechecagem obrigatória antes da alta da RPA. O plano também contempla o fortalecimento da interface com a TI para eliminar falhas na coleta dos dados. | G15: O hospital já iniciou a implementação da nova versão do protocolo em agosto, que estabelece condutas distintas conforme histórico de diabetes, faixas glicêmicas específicas e intervalos obrigatórios de rechecagem. Esse documento atualizado passa a ser o norte das equipes assistenciais e dos anestesistas, que também foram incluídos no cronograma de treinamentos e sensibilização, reforçando o papel de cada profissional no circuito de monitorização metabólica. A discussão com a TI para otimizar a coleta de dados e criar ferramentas/alertas no PEP permanece em andamento, visando ajustar os sistemas de prontuário para que as etapas críticas do protocolo se tornem etapas obrigatórias de preenchimento, reduzindo o risco de omissões. A execução inclui também a adequação do denominador do indicador, formalizando a exclusão de pacientes pediátricos até 13 anos e 11 meses e de pacientes internados em terapia intensiva, alinhando a métrica ao perfil correto da população-alvo. | J15: Serão auditados, os casos de hipoglicemia (<70 mg/dL) e hiperglicemia (>180 mg/dL) para verificar aderência ao ciclo completo do protocolo. Além disso, os relatórios de TI serão utilizados para mapear campos não preenchidos, horários de coleta incompatíveis e falhas de encadeamento entre pré, intra e pós-operatório. | M15: Implementar oficialmente a nova versão do protocolo publicada em agosto. Reforçar critérios de inclusão e exclusão: excluir pediátricos até 13 anos e 11 meses e pacientes de UTI do denominador. Auditar a aderência às novas diretrizes, principalmente aos fluxos de rechecagem. Investigar todos os casos sem coleta glicêmica, com análise das causas raiz. Implantar alertas eletrônicos para pacientes com glicemia <70 mg/dL ou >180 mg/dL, disparando checklists automáticos. Padronizar rechecagem: Não diabéticos com glicemia 70–139 mg/dL → encerrar protocolo. Diabéticos → repetir HGT a cada 2 horas até alta da RPA. Glicemias <70 ou >180 mg/dL → reavaliar de hora em hora.
A16: AGOSTO | B16: No mês de agosto, 887 pacientes foram incluídos no protocolo, dos 56 pacientes não tiveram avaliação glicêmica no período perioperatório. Entre os avaliados, 744 mantiveram o índice glicêmico dentro do preconizado em todas as aferições. Houve 89 pacientes com hipoglicemia (<70 mg/dL) na primeira coleta; 12 não foram reavaliados, 11 permaneceram entre 50–70 mg/dL no pós-operatório e 64 evoluíram para valores entre 70–133 mg/dL. Já 20 pacientes apresentaram hiperglicemia no pré-operatório (183–517 mg/dL); 6 permaneceram hiperglicêmicos no pós-operatório (186–402 mg/dL), enquanto 10 atingiram normoglicemia, entre 72–152 mg/dL. O mês demonstra bom desempenho clínico entre os pacientes monitorados, mas mantém como fragilidade a ausência de avaliação glicêmica para 56 indivíduos e falhas de rechecagem em parte dos casos com hipo e hiperglicemia.
A17: SETEMBRO | B17: 917 pacientes incluídos no protocolo, com 44 pacientes elegíveis sem qualquer avaliação glicêmica, demonstrando que a ausência de monitorização ainda permanece como fragilidade. Entre os avaliados, 756 mantiveram o índice glicêmico dentro do preconizado em todas as aferições. Houve 64 pacientes com glicemia <70 mg/dL na primeira coleta; desses, 17 não foram reavaliados, 3 permaneceram com valores entre 61–67 mg/dL no pós-operatório e 44 evoluíram para níveis entre 72–163 mg/dL, indicando correção adequada quando o ciclo de rechecagem foi seguido. Dos 813 pacientes com glicemia adequada no pré-operatório, 37 apresentaram hipoglicemia (<70 mg/dL) no pós-operatório e 20 apresentaram hiperglicemia (>190 mg/dL), demonstrando oscilações glicêmicas relacionadas ao manejo intraoperatório e ao estresse cirúrgico. No grupo com hiperglicemia inicial, 9 pacientes apresentaram valores entre 181–439 mg/dL; desses, 2 permaneceram hiperglicêmicos no pós-operatório (234–236 mg/dL), 1 não foi reavaliado e 5 atingiram normoglicemia, com resultados entre 79–178 mg/dL.
A18: MÊS | B18: Análise Critica | D18: Plan (Planejar) | G18: Do (Executar/Fazer) | J18: Check (Verificar/Checar) | M18: Act (Agir/Ajustar/Padronizar)
A19: OUTUBRO
A20: NOVEMBRO
A21: DEZEMBRO

Sheet % Saídas sem eventos anestésico
A1: ANO | C1: 2025
A2: SAÍDAS SEM EVENTOS RELACIONADOS AO ATO ANESTÉSICO | C2: 0.86 | D2: 0.86 | E2: 0.87 | F2: 0.89 | G2: 0.84 | H2: 0.88 | I2: 0.88 | J2: 0.88 | K2: 0.9 | O2: =MEDIAN(C2:N2) -> 0.88
A3: MÊS | C3: Janeiro | D3: Fevereiro | E3: Março | F3: Abril | G3: Maio | H3: Junho | I3: Julho | J3: Agosto | K3: Setembro | L3: Outubro | M3: Novembro | N3: Dezembro | O3: Média anual
A4: Nº de pacientes submetidos a procedimentos sob anestesia/sedação sem a ocorrência de eventos relacionados ao ato anestésico. | C4: 1265 | D4: 1319 | E4: 1328 | F4: 1436 | G4: 1356 | H4: 1343 | I4: 1561 | J4: 1520 | K4: 1633 | L4: 0 | M4: 0 | N4: 0 | O4: =MEDIAN(C4:N4) -> 1335.5
A5: Nº de pacientes submetidos a procedimentos sob anestesia/sedação. | C5: 1472 | D5: 1535 | E5: 1533 | F5: 1622 | G5: 1607 | H5: 1530 | I5: 1781 | J5: 1720 | K5: 1823 | L5: 0 | M5: 0 | N5: 0 | O5: =MEDIAN(C5:N5) -> 1534
A6: META | C6: >90%
A7: MÊS | B7: Análise Critica | D7: Plan (Planejar) | G7: Do (Executar/Fazer) | J7: Check (Verificar/Checar) | M7: Act (Agir/Ajustar/Padronizar)
A8: JANEIRO
A9: FEVEREIRO
A10: MARÇO
A11: ABRIL
A12: MAIO
A13: JUNHO
A14: JULHO
A15: AGOSTO
A16: SETEMBRO
A17: OUTUBRO
A18: NOVEMBRO
A19: DEZEMBRO

Sheet % Mortalidade Associada a anest
A1: Ano | C1: 2025
A2: MORTALIDADE ASSOCIADA A ANESTESIA EM 48 HORAS E ATÉ 30 DIAS | C2: 0 | D2: 0 | E2: 0 | F2: 0 | G2: 0 | H2: 0 | I2: 0.001 | J2: 0 | K2: 0 | O2: =MEDIAN(C2:N2) -> 0
A3: Mês | C3: Janeiro | D3: Fevereiro | E3: Março | F3: Abril | G3: Maio | H3: Junho | I3: Julho | J3: Agosto | K3: Setembro | L3: Outubro | M3: Novembro | N3: Dezembro | O3: Media Anual
A4: Nº de pacientes com desfecho desfecho óbito atribuível à anestesia em 48H horas até 30 dias do procedimento. | C4: 0 | D4: 0 | E4: 0 | F4: 0 | G4: 0 | H4: 0 | I4: 1 | J4: 0 | K4: 0 | L4: 0 | M4: 0 | N4: 0 | O4: =MEDIAN(C4:N4) -> 0
A5: Nº de pacientes submetidos a procedimentos sob anestesia/sedação. | C5: 1472 | D5: 1535 | E5: 1533 | F5: 1622 | G5: 1607 | H5: 1530 | I5: 1781 | J5: 1720 | K5: 1823 | L5: 0 | M5: 0 | N5: 0 | O5: =MEDIAN(C5:N5) -> 1534
A6: META
A7: MÊS | B7: Análise Critica
A8: Julho | B8: O evento de julho caracteriza-se como complicação cardiovascular aguda imprevisível, sem correlação com falhas de processo anestésico, estrutural ou de comunicação. A equipe atuou conforme os protocolos institucionais e diretrizes ASA, evidenciando resposta técnica adequada e cultura de segurança consolidada. O caso foi discutido em reunião multiprofissional com anestesia, endoscopia, hemodinâmica e gestão da qualidade, sendo classificado como evento não prevenível, com valor educativo para aprimoramento da vigilância cardiovascular em procedimentos endoscópicos sob anestesia geral. Descrição do Evento: Em 11/07/2025, paciente do sexo feminino, 53 anos, ASA II, foi encaminhada de outro município para CPRE de urgência devido a coledocolitíase múltipla. Durante o procedimento, após a retirada de cálculos, apresentou dessaturação súbita, instabilidade hemodinâmica e evolução para parada cardiorrespiratória (AESP/assistolia). As manobras de reanimação foram iniciadas imediatamente, com intubação orotraqueal, uso de drogas vasoativas e encaminhamento à hemodinâmica durante RCP contínua. Foram realizados cateterismo e arteriografia pulmonar, que descartaram TEP e evidenciaram suspeita de oclusão aguda da coronária direita. Após 40 minutos de suporte avançado de vida sem reversão, o óbito foi declarado às 21h. A análise do prontuário e discussão multiprofissional concluem que o evento se trata de óbito intraoperatório não evitável, decorrente de complicação cardíaca aguda imprevisível (provável infarto agudo de ventrículo direito) durante anestesia geral. Achados principais: Conduta técnica adequada: reanimação avançada, uso de aminas, ventilação mecânica, correção de causas reversíveis e transferência sob RCP para investigação. Investigação diagnóstica completa (descartado TEP, confirmada obstrução coronariana). Sem falha de processo identificável, sem indícios de imperícia, omissão ou falha de comunicação. Condições estruturais adequadas: sala equipada, equipe disponível, acionamento da hemodinâmica em tempo hábil.

Sheet % Estratificação de risco
A1: ANO | C1: 2025
A2: TAXA DE ESTRATIFICAÇÃO DE RISCO ANESTÉSICO DO SERVIÇO | C2: 1 | D2: 1 | E2: 1 | F2: 1 | G2: 1 | H2: 1 | I2: 1 | J2: 1 | K2: 1 | O2: =MEDIAN(C2:N2) -> 1
A3: Mês | C3: Janeiro | D3: Fevereiro | E3: Março | F3: Abril | G3: Maio | H3: Junho | I3: Julho | J3: Agosto | K3: Setembro | L3: Outubro | M3: Novembro | N3: Dezembro | O3: Média Anual
A4: Nº de pacientes submetidos a procedimentos sob anestesia/sedação com classificação ASA realizada na avaliação pré-anestésica. | C4: 1472 | D4: 1535 | E4: 1533 | F4: 1622 | G4: 1607 | H4: 1530 | I4: 1781 | J4: 1720 | K4: 1823 | L4: 0 | M4: 0 | N4: 0 | O4: =MEDIAN(C4:N4) -> 1534
A5: Nº de pacientes submetidos a procedimentos sob anestesia/sedação. | C5: 1472 | D5: 1535 | E5: 1533 | F5: 1622 | G5: 1607 | H5: 1530 | I5: 1781 | J5: 1720 | K5: 1823 | L5: 0 | M5: 0 | N5: 0 | O5: =MEDIAN(C5:N5) -> 1534
A6: META
A7: MÊS | B7: Análise Critica | D7: Plan (Planejar) | G7: Do (Executar/Fazer) | J7: Check (Verificar/Checar) | M7: Act (Agir/Ajustar/Padronizar)
A8: JANEIRO
A9: FEVEREIRO
A10: MARÇO
A11: ABRIL
A12: MAIO
A13: JUNHO
A14: JULHO
A15: AGOSTO
A16: SETEMBRO
A17: OUTUBRO
A18: NOVEMBRO
A19: DEZEMBRO

Sheet %Incidencia de VAD não prevista
A1: Ano | C1: 2025
A2: INCIDÊNCIA DE VIA ÁREA DIFÍCIL NÃO IDENTIFICADA NO PERÍODO INTRAOPERATÓRIO | C2: =C4/C5 -> 0 | D2: =D4/D5 -> 0 | E2: =E4/E5 -> 0 | F2: =F4/F5 -> 0 | G2: =G4/G5 -> 0.0021231423 | H2: =H4/H5 -> 0 | I2: =I4/I5 -> 0 | J2: =J4/J5 -> 0.0056390977 | K2: =K4/K5 -> 0.0055350554 | O2: =MEDIAN(C2:N2) -> 0
A3: MÊS | C3: Janeiro | D3: Fevereiro | E3: Março | F3: Abril | G3: Maio | H3: Junho | I3: Julho | J3: Agosto | K3: Setembro | L3: Outubro | M3: Novembro | N3: Dezembro | O3: Média Anual
A4: Nº de pacientes submetidos a procedimentos sob anestesia com necessidade de intubação identificada como difícil sem preditores prévios identificados. | C4: 0 | D4: 0 | E4: 0 | F4: 0 | G4: 1 | H4: 0 | I4: 0 | J4: 3 | K4: 3 | O4: =MEDIAN(C4:N4) -> 0
A5: Nº de pacientes submetidos a procedimento sob anestesia com necessidade de intubação. | C5: 473 | D5: 462 | E5: 444 | F5: 510 | G5: 471 | H5: 473 | I5: 538 | J5: 532 | K5: 542 | L5: 0 | M5: 0 | N5: 0 | O5: =MEDIAN(C5:N5) -> 472
A6: META
A7: MÊS | B7: Análise Critica | D7: Plan (Planejar) | G7: Do (Executar/Fazer) | J7: Check (Verificar/Checar) | M7: Act (Agir/Ajustar/Padronizar)
A8: JANEIRO
A9: FEVEREIRO
A10: MARÇO
A11: ABRIL
A12: MAIO
A13: JUNHO
A14: JULHO
A15: AGOSTO
A16: SETEMBRO
A17: OUTUBRO
A18: NOVEMBRO
A19: DEZEMBRO

Sheet % Incidência de NVPO
A1: ANO | C1: 2025
A2: TAXA DE INCIDÊNCIA DE NÁUSEA E VÔMITO NO PERÍODO INTRAOPERATÓRIO ATÉ A ALTA ANESTÉSICA | C2: =C4/C5 -> 0.051843318 | D2: =D4/D5 -> 0.058378378 | E2: =E4/E5 -> 0.063321386 | F2: =F4/F5 -> 0.045263158 | G2: =G4/G5 -> 0.064189189 | H2: =H4/H5 -> 0.054466231 | I2: =I4/I5 -> 0.058341863 | J2: =J4/J5 -> 0.052465897 | K2: =K4/K5 -> 0.039274924 | O2: =MEDIAN(C2:N2) -> 0.054466231
A3: MêS | C3: Janeiro | D3: Fevereiro | E3: Março | F3: Abril | G3: Maio | H3: Junho | I3: Julho | J3: Agosto | K3: Setembro | L3: Outubro | M3: Novembro | N3: Dezembro | O3: Média Anual
A4: Nº de pacientes submetidos a procedimentos sob anestesia/sedação elegíveis ao protocolo de prevenção de náusea e vômitos e que apresentaram náusea e vômitos no período intraoperatório até a alta anestésica. | C4: 45 | D4: 54 | E4: 53 | F4: 43 | G4: 57 | H4: 50 | I4: 57 | J4: 50 | K4: 39 | L4: 0 | M4: 0 | N4: 0 | O4: =MEDIAN(C4:N4) -> 47.5
A5: Nº de pacientes submetidos a procedimentos sob anestesia/sedação elegíveis ao protocolo de prevenção de náusea e vômitos. | C5: 868 | D5: 925 | E5: 837 | F5: 950 | G5: 888 | H5: 918 | I5: 977 | J5: 953 | K5: 993 | L5: 0 | M5: 0 | N5: 0 | O5: =MEDIAN(C5:N5) -> 903
A6: META
A7: MÊS | B7: Análise Critica | D7: Plan (Planejar) | G7: Do (Executar/Fazer) | J7: Check (Verificar/Checar) | M7: Act (Agir/Ajustar/Padronizar)
A8: JANEIRO
A9: FEVEREIRO
A10: MARÇO
A11: ABRIL
A12: MAIO
A13: JUNHO
A14: JULHO
A15: AGOSTO
A16: SETEMBRO
A17: OUTUBRO
A18: NOVEMBRO
A19: DEZEMBRO

Sheet %Efetiv. no manejo de Int. Anes
A1: EFETIVIDADE DO PROTOCOLO DE MANEJO DE INTOXICAÇÃO POR ANESTÉSICOS LOCAIS | C1: 2025
C2: 1 | D2: 1 | E2: 1 | F2: 1 | G2: 1 | H2: 1 | I2: 1 | J2: 1 | K2: 1 | O2: =MEDIAN(C2:N2) -> 1
A3: MÊS | C3: Janeiro | D3: Fevereiro | E3: Março | F3: Abril | G3: Maio | H3: Junho | I3: Julho | J3: Agosto | K3: Setembro | L3: Outubro | M3: Novembro | N3: Dezembro | O3: Média Anual
A4: Nº de pacientes submetidos a cirurgia sob anestesia que tenham apresentado sinais e sintomas de intoxicação e cujo manejo para tratamento foi instituído com sucesso. | C4: 0 | D4: 0 | E4: 0 | F4: 0 | G4: 0 | H4: 0 | I4: 0 | J4: 0 | K4: 1 | L4: 0 | M4: 0 | N4: 0 | O4: =MEDIAN(C4:N4) -> 0
A5: Nº de pacientes submetidos a cirurgia sob anestesia que tenham apresentado sinais e sintomas de intoxicação. | C5: 0 | D5: 0 | E5: 0 | F5: 0 | G5: 0 | H5: 0 | I5: 0 | J5: 0 | K5: 1 | L5: 0 | M5: 0 | N5: 0 | O5: =MEDIAN(C5:N5) -> 0
A6: META

Sheet % Conformidade do ATB
A1: TAXA DE CONFORMIDADE DA PROFILAXIA ANTIMICROBIANA CIRÚRGICA DURANTE O PROCEDIMENTO | C1: 2025
C2: 0.87 | D2: 0.87 | E2: 0.91 | F2: 0.89 | G2: 0.89 | H2: 0.88 | I2: 0.91 | J2: 0.9 | K2: 0.89 | O2: =MEDIAN(C2:N2) -> 0.89
A3: MÊS | C3: Janeiro | D3: Fevereiro | E3: Março | F3: Abril | G3: Maio | H3: Junho | I3: Julho | J3: Agosto | K3: Setembro | L3: Outubro | M3: Novembro | N3: Dezembro | O3: Média Anual
A4: Nº de pacientes submetidos a procedimentos sob anestesia/sedação com dose inicial e repique de antibiótico profilático realizada conforme protocolo institucional. | C4: 634 | D4: 660 | E4: 740 | F4: 810 | G4: 837 | H4: 751 | I4: 795 | J4: 809 | K4: 807 | L4: 0 | M4: 0 | N4: 0 | O4: =MEDIAN(C4:N4) -> 745.5
A5: Nº de pacientes submetidos a procedimentos sob anestesia/sedação elegíveis ao protocolo de antibioticoprofilaxia institucional. | C5: 732 | D5: 760 | E5: 817 | F5: 906 | G5: 943 | H5: 856 | I5: 876 | J5: 899 | K5: 904 | L5: 0 | M5: 0 | N5: 0 | O5: =MEDIAN(C5:N5) -> 836.5
A6: META | C6: >90%
A7: MÊS | B7: Análise Critica | D7: Plan (Planejar) | G7: Do (Executar/Fazer) | J7: Check (Verificar/Checar) | M7: Act (Agir/Ajustar/Padronizar)
A8: JANEIRO
A9: FEVEREIRO
A10: MARÇO
A11: ABRIL
A12: MAIO
A13: JUNHO
A14: JULHO
A15: AGOSTO
A16: SETEMBRO
A17: OUTUBRO
A18: NOVEMBRO
A19: DEZEMBRO

Sheet % adesão aos prot.segurança
A1: TAXA DE ADESÃO AOS PROTOCOLOS SEGURANÇA | C1: 2025
C2: =C4/C5 -> 0.91331178 | D2: =D4/D5 -> 0.91440559 | E2: =E4/E5 -> 0.92696321 | F2: =F4/F5 -> 0.90945573 | G2: =G4/G5 -> 0.92497482 | H2: =H4/H5 -> 0.91330698 | I2: =I4/I5 -> 0.94478528 | J2: =J4/J5 -> 0.94006934 | K2: =K4/K5 -> 0.93551469
A3: MÊS | C3: Janeiro | D3: Fevereiro | E3: Março | F3: Abril | G3: Maio | H3: Junho | I3: Julho | J3: Agosto | K3: Setembro | L3: Outubro | M3: Novembro | N3: Dezembro | O3: Média Anual
A4: Numerador: Nº de protocolos de seguranç​a cumpridos conforme padrão | C4: 3108 | D4: 3269 | E4: 3376 | F4: 3626 | G4: 3674 | H4: 3466 | I4: 3850 | J4: 3796 | K4: 3917
A5: Denominador: N° de protocolos de segurança avaliados | C5: 3403 | D5: 3575 | E5: 3642 | F5: 3987 | G5: 3972 | H5: 3795 | I5: 4075 | J5: 4038 | K5: 4187
A6: META | C6: 0.95
A7: Protocolo | C7: Janeiro | D7: Fevereiro | E7: Março | F7: Abril | G7: Maio | H7: Junho | I7: Julho | J7: Agosto | K7: Setembro | L7: Outubro | M7: Novembro | N7: Dezembro
A8: 1 | B8: Cirurgia Segura - Numerador | K8: 8
B9: Cirurgia Segura - Denominador | K9: 11
A10: 2 | B10: Via Aérea Difícil - Denominador | C10: 473 | D10: 462 | E10: 444 | F10: 510 | G10: 471 | H10: 473 | I10: 538 | J10: 532 | K10: 542 | L10: 0 | M10: 0 | N10: 0
B11: Via Aérea Difícil - Numerador | C11: 473 | D11: 462 | E11: 444 | F11: 510 | G11: 470 | H11: 473 | I11: 538 | J11: 529 | K11: 539 | L11: 0 | M11: 0 | N11: 0
A12: 3 | B12: Antibioticoprofilaxia Cirúrgica - Numerador | C12: 634 | D12: 660 | E12: 740 | F12: 810 | G12: 837 | H12: 751 | I12: 795 | J12: 809 | K12: 807 | L12: 0 | M12: 0 | N12: 0
B13: Antibioticoprofilaxia Cirúrgica - Denominador | C13: 732 | D13: 760 | E13: 817 | F13: 906 | G13: 943 | H13: 856 | I13: 876 | J13: 899 | K13: 904 | L13: 0 | M13: 0 | N13: 0
A14: 4 | B14: Controle Glicêmico no Paciente Cirúrgico - Numerador | C14: 535 | D14: 619 | E14: 662 | F14: 688 | G14: 764 | H14: 717 | I14: 740 | J14: 744 | K14: 756 | L14: 0 | M14: 0 | N14: 0
B15: Controle Glicêmico no Paciente Cirúrgico - Denominador | C15: 726 | D15: 818 | E15: 848 | F15: 949 | G15: 951 | H15: 936 | I15: 880 | J15: 887 | K15: 917 | L15: 0 | M15: 0 | N15: 0
A16: 5 | B16: Prevenção de Hipotermia - Numerador | C16: 1466 | D16: 1528 | E16: 1530 | F16: 1618 | G16: 1603 | H16: 1525 | I16: 1777 | J16: 1714 | K16: 1814 | L16: 0 | M16: 0 | N16: 0
B17: Prevenção de Hipotermia - Denominador | C17: 1472 | D17: 1535 | E17: 1533 | F17: 1622 | G17: 1607 | H17: 1530 | I17: 1781 | J17: 1720 | K17: 1823 | L17: 0 | M17: 0 | N17: 0
A18: 6 | B18: Manejo de Intoxicação por Anestésicos Locais - Numerador | C18: 0 | D18: 0 | E18: 0 | F18: 0 | G18: 0 | H18: 0 | I18: 0 | J18: 0 | K18: 1 | L18: 0 | M18: 0 | N18: 0
B19: Manejo de Intoxicação por Anestésicos Locais - Denominador | C19: 0 | D19: 0 | E19: 0 | F19: 0 | G19: 0 | H19: 0 | I19: 0 | J19: 0 | K19: 1 | L19: 0 | M19: 0 | N19: 0
A20: 7 | B20: Hipertermia Maligna - Numerador | C20: 0 | D20: 0 | E20: 0 | F20: 0 | G20: 0 | H20: 0 | I20: 0 | J20: 0 | K20: 0 | L20: 0 | M20: 0 | N20: 0
B21: Hipertermia Maligna - Denominador | C21: 0 | D21: 0 | E21: 0 | F21: 0 | G21: 0 | H21: 0 | I21: 0 | J21: 0 | K21: 0 | L21: 0 | M21: 0 | N21: 0
A22: 8 | B22: Alergia ao Látex - Numerador | C22: 0 | D22: 0 | E22: 0 | F22: 0 | G22: 0 | H22: 0 | I22: 0 | J22: 0 | K22: 0 | L22: 0 | M22: 0 | N22: 0
B23: Alergia ao Látex - Denominador | C23: 0 | D23: 0 | E23: 0 | F23: 0 | G23: 0 | H23: 0 | I23: 0 | J23: 0 | K23: 0 | L23: 0 | M23: 0 | N23: 0
A24: 9 | B24: Prevenção de Eventos Hemorrágicos - Numerador
B25: Prevenção de Eventos Hemorrágicos - Denominador
A26: 10 | B26: Prevenção de Tromboembolismo Venoso (TEV) - Numerador | I26: 6 | J26: 12 | K26: 13
B27: Prevenção de Tromboembolismo Venoso (TEV) - Denominador | I27: 10 | J27: 15 | K27: 16
A28: 11 | B28: Transferência Intra-hospitalar Segura - Numerador | I28: 8 | J28: 12 | K28: 17
B29: Transferência Intra-hospitalar Segura - Denominador | I29: 10 | J29: 15 | K29: 27

Sheet % Efet. Prevenção Cefaléia PPD
A1: EFETIVIDADE DO PROTOCOLO DE PREVENÇÃO DE CAFALÉIA PÓS PUNÇÃO DURAL | C1: 2025
C2: 1 | D2: 1 | E2: 1 | F2: 1 | G2: 0.99 | H2: 1 | I2: 0.97 | J2: 0.99 | K2: 1 | O2: =MEDIAN(C2:N2) -> 1
A3: MÊS | C3: Janeiro | D3: Fevereiro | E3: Março | F3: Abril | G3: Maio | H3: Junho | I3: Julho | J3: Agosto | K3: Setembro | L3: Outubro | M3: Novembro | N3: Dezembro | O3: Média Anual
A4: Nº de pacientes em pós punção dural (intencional ou inadvertida) para fins de anestesia que não apresentaram cefaléia. | C4: 129 | D4: 126 | E4: 204 | F4: 148 | G4: 84 | H4: 97 | I4: 87 | J4: 117 | K4: 91 | L4: 0 | M4: 0 | N4: 0 | O4: =MEDIAN(C4:N4) -> 94
A5: Nº de pacientes em pós punção dural (intencional ou inadvertida) para fins de anestesia. | C5: 129 | D5: 126 | E5: 204 | F5: 148 | G5: 85 | H5: 97 | I5: 90 | J5: 118 | K5: 91 | L5: 0 | M5: 0 | N5: 0 | O5: =MEDIAN(C5:N5) -> 94
A6: META
A7: MÊS | B7: Análise Critica | D7: Plan (Planejar) | G7: Do (Executar/Fazer) | J7: Check (Verificar/Checar) | M7: Act (Agir/Ajustar/Padronizar)
A8: JANEIRO
A9: FEVEREIRO
A10: MARÇO
A11: ABRIL
A12: MAIO
A13: JUNHO
A14: JULHO
A15: AGOSTO
A16: SETEMBRO
A17: OUTUBRO
A18: NOVEMBRO
A19: DEZEMBRO

Sheet % Incidência de Hipotermia
A1: TAXA DE INCIDÊNCIA DE HIPOTERMIA NÃO INTENCIONAL NO PERÍODO INTRAOPERATÓRIO ATÉ A ALTA ANESTÉSICA | C1: 2025
C2: =C4/C5 -> 0.004076087 | D2: =D4/D5 -> 0.0045602606 | E2: =E4/E5 -> 0.0019569472 | F2: =F4/F5 -> 0.0024660912 | G2: =G4/G5 -> 0.0024891101 | H2: =H4/H5 -> 0.0032679739 | I2: =I4/I5 -> 0.0022459293 | J2: =J4/J5 -> 0.0034883721 | K2: =K4/K5 -> 0.0049369172 | O2: =MEDIAN(C2:N2) -> 0.0032679739
A3: MÊS | C3: Janeiro | D3: Fevereiro | E3: Março | F3: Abril | G3: Maio | H3: Junho | I3: Julho | J3: Agosto | K3: Setembro | L3: Outubro | M3: Novembro | N3: Dezembro | O3: Média Anual
A4: Nº de pacientes que apresentaram hipotermia não intencional no período intraoperatório até a alta anestésica. | C4: 6 | D4: 7 | E4: 3 | F4: 4 | G4: 4 | H4: 5 | I4: 4 | J4: 6 | K4: 9 | L4: 0 | M4: 0 | N4: 0 | O4: =MEDIAN(C4:N4) -> 4
A5: Nº de pacientes submetidos a procedimentos sob anestesia/sedação. | C5: 1472 | D5: 1535 | E5: 1533 | F5: 1622 | G5: 1607 | H5: 1530 | I5: 1781 | J5: 1720 | K5: 1823 | L5: 0 | M5: 0 | N5: 0 | O5: =MEDIAN(C5:N5) -> 1534
A6: META
A7: MÊS | B7: Análise Critica | D7: Plan (Planejar) | G7: Do (Executar/Fazer) | J7: Check (Verificar/Checar) | M7: Act (Agir/Ajustar/Padronizar)
A8: JANEIRO
A9: FEVEREIRO
A10: MARÇO
A11: ABRIL
A12: MAIO
A13: JUNHO
A14: JULHO
A15: AGOSTO
A16: SETEMBRO
A17: OUTUBRO
A18: NOVEMBRO
A19: DEZEMBRO

Sheet % adesão aos prot clinico Assit
A1: TAXA DE ADESÃO AOS PROTOCOLOS CLÍNICOS ASSISTENCIAIS | C1: 2025
C2: =C4/C5 -> 0.82763115 | D2: =D4/D5 -> 0.83924647 | E2: =E4/E5 -> 0.82133006 | F2: =F4/F5 -> 0.84570766 | G2: =G4/G5 -> 0.80821513 | H2: =H4/H5 -> 0.82384342 | I2: =I4/I5 -> 0.84368009 | J2: =J4/J5 -> 0.83897605 | K2: =K4/K5 -> 0.8411389 | O2: =O4/O5 -> 0.8161266
A3: MÊS | C3: Janeiro | D3: Fevereiro | E3: Março | F3: Abril | G3: Maio | H3: Junho | I3: Julho | J3: Agosto | K3: Setembro | L3: Outubro | M3: Novembro | N3: Dezembro | O3: Média Anual
A4: Numerador: Nº de protocolos de clínicos/assistenciais conforme padraão | C4: =C8+C10+C12+C14 -> 2540 | D4: =D8+D10+D12+D14 -> 2673 | E4: =E8+E10+E12+E14 -> 2680 | F4: =F8+F10+F12+F14 -> 2916 | G4: =G8+G10+G12+G14 -> 2735 | H4: =H8+H10+H12+H14 -> 2778 | I4: =I8+I10+I12+I14 -> 3017 | J4: =J8+J10+J12+J14 -> 3048 | ... N4: =N8+N10+N12+N14 -> 0 | O4: =MEDIAN(C4:N4) -> 2707.5
A5: Denominador: N° de protocolos de clínicos assistenciais | C5: =C9+C11+C13+C15 -> 3069 | D5: =D9+D11+D13+D15 -> 3185 | E5: =E9+E11+E13+E15 -> 3263 | F5: =F9+F11+F13+F15 -> 3448 | G5: =G9+G11+G13+G15 -> 3384 | H5: =H9+H11+H13+H15 -> 3372 | I5: =I9+I11+I13+I15 -> 3576 | J5: =J9+J11+J13+J15 -> 3633 | ... N5: =N9+N11+N13+N15 -> 0 | O5: =MEDIAN(C5:N5) -> 3317.5
A6: META | C6: 0.95
A7: Protocolos | C7: Janeiro | D7: Fevereiro | E7: Março | F7: Abril | G7: Maio | H7: Junho | I7: Julho | J7: Agosto | K7: Setembro | L7: Outubro | M7: Novembro | N7: Dezembro | O7: Média Anual
A8: 1 | B8: Manejo da Dor Aguda no Pós-operatório - Numerador | C8: =C9-'% Incidencia de dor aguda'!C4 -> 1397 | D8: =D9-'% Incidencia de dor aguda'!D4 -> 1468 | E8: =E9-'% Incidencia de dor aguda'!E4 -> 1471 | F8: =F9-'% Incidencia de dor aguda'!F4 -> 1566 | G8: =G9-'% Incidencia de dor aguda'!G4 -> 1511 | H8: =H9-'% Incidencia de dor aguda'!H4 -> 1479 | I8: =I9-'% Incidencia de dor aguda'!I4 -> 1717 | J8: =J9-'% Incidencia de dor aguda'!J4 -> 1662 | ... O8: =O9-'% Incidencia de dor aguda'!O4 -> 1474
B9: Manejo da Dor Aguda no Pós-operatório - Denominador | C9: ='% Incidencia de dor aguda'!C5 -> 1472 | D9: ='% Incidencia de dor aguda'!D5 -> 1535 | E9: ='% Incidencia de dor aguda'!E5 -> 1533 | F9: ='% Incidencia de dor aguda'!F5 -> 1622 | G9: ='% Incidencia de dor aguda'!G5 -> 1607 | H9: ='% Incidencia de dor aguda'!H5 -> 1530 | I9: ='% Incidencia de dor aguda'!I5 -> 1781 | J9: ='% Incidencia de dor aguda'!J5 -> 1720 | ... O9: ='% Incidencia de dor aguda'!O5 -> 1534
A10: 2 | B10: Abreviação de Jejum - Numerador | C10: ='% Abreviação do jejum P.'!C4 -> 191 | D10: ='% Abreviação do jejum P.'!D4 -> 208 | E10: ='% Abreviação do jejum P.'!E4 -> 221 | F10: ='% Abreviação do jejum P.'!F4 -> 295 | G10: ='% Abreviação do jejum P.'!G4 -> 309 | H10: ='% Abreviação do jejum P.'!H4 -> 334 | I10: ='% Abreviação do jejum P.'!I4 -> 293 | J10: ='% Abreviação do jejum P.'!J4 -> 366 | ... O10: ='% Abreviação do jejum P.'!O4 -> 257
B11: Abreviação de Jejum - Denominador | C11: ='% Abreviação do jejum P.'!C5 -> 600 | D11: ='% Abreviação do jejum P.'!D5 -> 599 | E11: ='% Abreviação do jejum P.'!E5 -> 689 | F11: ='% Abreviação do jejum P.'!F5 -> 728 | G11: ='% Abreviação do jejum P.'!G5 -> 804 | H11: ='% Abreviação do jejum P.'!H5 -> 827 | I11: ='% Abreviação do jejum P.'!I5 -> 728 | J11: ='% Abreviação do jejum P.'!J5 -> 842 | ... O11: ='% Abreviação do jejum P.'!O5 -> 708.5
A12: 3 | B12: Prevenção de Náuseas e Vômitos no Pós-operatório (PONV) - Numerador | C12: =C13-'% Incidência de NVPO'!C4 -> 823 | D12: =D13-'% Incidência de NVPO'!D4 -> 871 | E12: =E13-'% Incidência de NVPO'!E4 -> 784 | F12: =F13-'% Incidência de NVPO'!F4 -> 907 | G12: =G13-'% Incidência de NVPO'!G4 -> 831 | H12: =H13-'% Incidência de NVPO'!H4 -> 868 | I12: =I13-'% Incidência de NVPO'!I4 -> 920 | J12: =J13-'% Incidência de NVPO'!J4 -> 903 | ... O12: =O13-'% Incidência de NVPO'!O4 -> 855.5
B13: Prevenção de Náuseas e Vômitos no Pós-operatório (PONV) - Denominador | C13: ='% Incidência de NVPO'!C5 -> 868 | D13: ='% Incidência de NVPO'!D5 -> 925 | E13: ='% Incidência de NVPO'!E5 -> 837 | F13: ='% Incidência de NVPO'!F5 -> 950 | G13: ='% Incidência de NVPO'!G5 -> 888 | H13: ='% Incidência de NVPO'!H5 -> 918 | I13: ='% Incidência de NVPO'!I5 -> 977 | J13: ='% Incidência de NVPO'!J5 -> 953 | ... O13: ='% Incidência de NVPO'!O5 -> 903
A14: 4 | B14: Manejo de Cefaleia Pós-raqui - Numerador | C14: ='% Efet. Prevenção Cefaléia PPD'!C4 -> 129 | D14: ='% Efet. Prevenção Cefaléia PPD'!D4 -> 126 | E14: ='% Efet. Prevenção Cefaléia PPD'!E4 -> 204 | F14: ='% Efet. Prevenção Cefaléia PPD'!F4 -> 148 | G14: ='% Efet. Prevenção Cefaléia PPD'!G4 -> 84 | H14: ='% Efet. Prevenção Cefaléia PPD'!H4 -> 97 | I14: ='% Efet. Prevenção Cefaléia PPD'!I4 -> 87 | J14: ='% Efet. Prevenção Cefaléia PPD'!J4 -> 117 | ... O14: ='% Efet. Prevenção Cefaléia PPD'!O4 -> 94
B15: Manejo de Cefaleia Pós-raqui - Denominador | C15: ='% Efet. Prevenção Cefaléia PPD'!C5 -> 129 | D15: ='% Efet. Prevenção Cefaléia PPD'!D5 -> 126 | E15: ='% Efet. Prevenção Cefaléia PPD'!E5 -> 204 | F15: ='% Efet. Prevenção Cefaléia PPD'!F5 -> 148 | G15: ='% Efet. Prevenção Cefaléia PPD'!G5 -> 85 | H15: ='% Efet. Prevenção Cefaléia PPD'!H5 -> 97 | I15: ='% Efet. Prevenção Cefaléia PPD'!I5 -> 90 | J15: ='% Efet. Prevenção Cefaléia PPD'!J5 -> 118 | ... O15: ='% Efet. Prevenção Cefaléia PPD'!O5 -> 94

Sheet Indicadores estratégicos

Sheet Resultados Gerais
B1: Classificação (Donabedian) | C1: Tipo Funcional | D1: INDICADOR | E1: META ESTABELECIDA | F1: Janeiro | G1: Fevereiro | H1: Março | I1: Abril | J1: Maio | K1: Junho | L1: Julho | M1: Agosto | N1: Setembro | O1: Outubro | P1: Novembro | Q1: Dezembro | R1: Média Anual
A2: 1 | B2: Processo | C2: Efetividade clínica | D2: ='% Consulta pré anestésica'!A2 -> TAXA DE PROCEDIMENTOS ELETIVOS COM CONSULTA PRÉ-ANESTÉSICA AMBULATORIAL | E2: ≥95% | F2: ='% Consulta pré anestésica'!C2 -> 0.79517191 | G2: ='% Consulta pré anestésica'!D2 -> 0.79330007 | H2: ='% Consulta pré anestésica'!E2 -> 0.75690236 | I2: ='% Consulta pré anestésica'!F2 -> 0.84649123 | J2: ='% Consulta pré anestésica'!G2 -> 0.85654513 | K2: ='% Consulta pré anestésica'!H2 -> 0.96018277 | L2: ='% Consulta pré anestésica'!I2 -> 0.95281996 | M2: ='% Consulta pré anestésica'!J2 -> 0.97834758 | N2: ='% Consulta pré anestésica'!K2 -> 0.97022198 | R2: ='% Consulta pré anestésica'!O2 -> 0.85654513
A3: 2 | B3: Resultado | C3: Efetividade clínica | D3: ='% Incidencia de dor aguda'!A1 -> INCIDÊNCIA DE DOR AGUDA NO PERÍODO INTRAOPERATÓRIO ATÉ A ALTA ANESTÉSICA | E3: ≤10% | F3: ='% Incidencia de dor aguda'!C2 -> 0.050951087 | G3: ='% Incidencia de dor aguda'!D2 -> 0.043648208 | H3: ='% Incidencia de dor aguda'!E2 -> 0.040443575 | I3: ='% Incidencia de dor aguda'!F2 -> 0.034525277 | J3: ='% Incidencia de dor aguda'!G2 -> 0.059738643 | K3: ='% Incidencia de dor aguda'!H2 -> 0.033333333 | L3: ='% Incidencia de dor aguda'!I2 -> 0.035934868 | M3: ='% Incidencia de dor aguda'!J2 -> 0.03372093 | N3: ='% Incidencia de dor aguda'!K2 -> 0.036752606 | R3: ='% Incidencia de dor aguda'!O2 -> 0.036752606
A4: 3 | B4: Processo | C4: Efetividade clínica | D4: ='% Abreviação do jejum P.'!A1 -> INCIDÊNCIA DE ABREVIAÇÃO DO JEJUM PROLONGADO | E4: ≥60% | F4: ='% Abreviação do jejum P.'!C2 -> 0.32 | G4: ='% Abreviação do jejum P.'!D2 -> 0.35 | H4: ='% Abreviação do jejum P.'!E2 -> 0.32 | I4: ='% Abreviação do jejum P.'!F2 -> 0.41 | J4: ='% Abreviação do jejum P.'!G2 -> 0.38 | K4: ='% Abreviação do jejum P.'!H2 -> 0.4 | L4: ='% Abreviação do jejum P.'!I2 -> 0.4 | M4: ='% Abreviação do jejum P.'!J2 -> 0.43 | N4: ='% Abreviação do jejum P.'!K2 -> 0.42 | R4: ='% Abreviação do jejum P.'!O2 -> 0.4
A5: 4 | B5: Resultado | C5: Segurança do paciente | D5: ='Incidencia de PCR até a Alta'!A1 -> INCIDÊNCIA DE PARADA CARDIORRESPIRATÓRIA NO PERÍODO DA INDUÇÃO ATÉ A ALTA ANESTÉSICA | E5: Meta zero / ≤1/10.000 anestesias | F5: ='Incidencia de PCR até a Alta'!C2 -> 0 | G5: ='Incidencia de PCR até a Alta'!D2 -> 0 | H5: ='Incidencia de PCR até a Alta'!E2 -> 0 | I5: ='Incidencia de PCR até a Alta'!F2 -> 0 | J5: ='Incidencia de PCR até a Alta'!G2 -> 0 | K5: ='Incidencia de PCR até a Alta'!H2 -> 0 | L5: ='Incidencia de PCR até a Alta'!I2 -> 0 | M5: ='Incidencia de PCR até a Alta'!J2 -> 0.00058139535 | N5: ='Incidencia de PCR até a Alta'!K2 -> 0.00054854635 | R5: ='Incidencia de PCR até a Alta'!O2 -> 0
A6: 5 | B6: Processo | C6: Efetividade clínica | D6: ='% Mudança da Tecnica Anestésica'!A1 -> TAXA DE MUDANÇA DE TÉCNICA ANESTÉSICA | E6: <5% | F6: ='% Mudança da Tecnica Anestésica'!C2 -> 0 | G6: ='% Mudança da Tecnica Anestésica'!D2 -> 0 | H6: ='% Mudança da Tecnica Anestésica'!E2 -> 0 | I6: ='% Mudança da Tecnica Anestésica'!F2 -> 0 | J6: ='% Mudança da Tecnica Anestésica'!G2 -> 0 | K6: ='% Mudança da Tecnica Anestésica'!H2 -> 0 | L6: ='% Mudança da Tecnica Anestésica'!I2 -> 0 | M6: ='% Mudança da Tecnica Anestésica'!J2 -> 0 | N6: ='% Mudança da Tecnica Anestésica'!K2 -> 0.001 | R6: ='% Mudança da Tecnica Anestésica'!O2 -> 0
A7: 6 | B7: Resultado | C7: Segurança do paciente | D7: ='% Incidência Enc. UTI'!A2 -> INCIDÊNCIA DE PACIENTES ENCAMINHADOS PARA UTI SEM PLANEJAMENTO PRÉVIO COM INDICAÇÃO DECORRENTE DE EVENTOS ANESTÉSICOS | E7: Meta zero / ≤0,3% | F7: ='% Incidência Enc. UTI'!C2 -> 0.00071428571 | G7: ='% Incidência Enc. UTI'!D2 -> 0 | H7: ='% Incidência Enc. UTI'!E2 -> 0.00066622252 | I7: ='% Incidência Enc. UTI'!F2 -> 0.00062460962 | J7: ='% Incidência Enc. UTI'!G2 -> 0.0023837902 | K7: ='% Incidência Enc. UTI'!H2 -> 0.0012903226 | L7: ='% Incidência Enc. UTI'!I2 -> 0.0021401819 | M7: ='% Incidência Enc. UTI'!J2 -> 0.0011267606 | N7: ='% Incidência Enc. UTI'!K2 -> 0.0010723861 | R7: ='% Incidência Enc. UTI'!O2 -> 0.0010723861
A8: 7 | B8: Processo | C8: Efetividade clínica | D8: ='% Efet. no controle glicemico'!A2 -> EFETIVIDADE DO PROTOCOLO DE CONTROLE GLICÊMICO NO PERÍODO PERIOPERATÓRIO | E8: ≥90% | F8: ='% Efet. no controle glicemico'!C2 -> 0.74 | G8: ='% Efet. no controle glicemico'!D2 -> 0.76 | H8: ='% Efet. no controle glicemico'!E2 -> 0.78 | I8: ='% Efet. no controle glicemico'!F2 -> 0.72 | J8: ='% Efet. no controle glicemico'!G2 -> 0.8 | K8: ='% Efet. no controle glicemico'!H2 -> 0.77 | L8: ='% Efet. no controle glicemico'!I2 -> 0.91 | M8: ='% Efet. no controle glicemico'!J2 -> 0.83878241 | N8: ='% Efet. no controle glicemico'!K2 -> 0.82442748 | R8: ='% Efet. no controle glicemico'!O2 -> 0.78
A9: 8 | B9: Resultado | C9: Segurança do paciente | D9: ='% Saídas sem eventos anestésico'!A2 -> SAÍDAS SEM EVENTOS RELACIONADOS AO ATO ANESTÉSICO | E9: >90% | F9: ='% Saídas sem eventos anestésico'!C2 -> 0.86 | G9: ='% Saídas sem eventos anestésico'!D2 -> 0.86 | H9: ='% Saídas sem eventos anestésico'!E2 -> 0.87 | I9: ='% Saídas sem eventos anestésico'!F2 -> 0.89 | J9: ='% Saídas sem eventos anestésico'!G2 -> 0.84 | K9: ='% Saídas sem eventos anestésico'!H2 -> 0.88 | L9: ='% Saídas sem eventos anestésico'!I2 -> 0.88 | M9: ='% Saídas sem eventos anestésico'!J2 -> 0.88 | N9: ='% Saídas sem eventos anestésico'!K2 -> 0.9 | R9: ='% Saídas sem eventos anestésico'!O2 -> 0.88
A10: 9 | B10: Resultado | C10: Segurança do paciente | D10: ='% Mortalidade Associada a anest'!A2 -> MORTALIDADE ASSOCIADA A ANESTESIA EM 48 HORAS E ATÉ 30 DIAS | E10: Meta zero / ≤1/100.000 em 48h e ≤5/100.000 em 30d | F10: ='% Mortalidade Associada a anest'!C2 -> 0 | G10: ='% Mortalidade Associada a anest'!D2 -> 0 | H10: ='% Mortalidade Associada a anest'!E2 -> 0 | I10: ='% Mortalidade Associada a anest'!F2 -> 0 | J10: ='% Mortalidade Associada a anest'!G2 -> 0 | K10: ='% Mortalidade Associada a anest'!H2 -> 0 | L10: ='% Mortalidade Associada a anest'!I2 -> 0.001 | M10: ='% Mortalidade Associada a anest'!J2 -> 0 | N10: ='% Mortalidade Associada a anest'!K2 -> 0 | R10: ='% Mortalidade Associada a anest'!O2 -> 0
A11: 10 | B11: Processo | C11: Efetividade clínica | D11: ='% Estratificação de risco'!A2 -> TAXA DE ESTRATIFICAÇÃO DE RISCO ANESTÉSICO DO SERVIÇO | E11: ≥98–100% | F11: ='% Estratificação de risco'!C2 -> 1 | G11: ='% Estratificação de risco'!D2 -> 1 | H11: ='% Estratificação de risco'!E2 -> 1 | I11: ='% Estratificação de risco'!F2 -> 1 | J11: ='% Estratificação de risco'!G2 -> 1 | K11: ='% Estratificação de risco'!H2 -> 1 | L11: ='% Estratificação de risco'!I2 -> 1 | M11: ='% Estratificação de risco'!J2 -> 1 | N11: ='% Estratificação de risco'!K2 -> 1 | R11: ='% Estratificação de risco'!O2 -> 1
A12: 11 | B12: Resultado | C12: Segurança do paciente | D12: ='%Incidencia de VAD não prevista'!A2 -> INCIDÊNCIA DE VIA ÁREA DIFÍCIL NÃO IDENTIFICADA NO PERÍODO INTRAOPERATÓRIO | E12: ≤2% | F12: ='%Incidencia de VAD não prevista'!C2 -> 0 | G12: ='%Incidencia de VAD não prevista'!D2 -> 0 | H12: ='%Incidencia de VAD não prevista'!E2 -> 0 | I12: ='%Incidencia de VAD não prevista'!F2 -> 0 | J12: ='%Incidencia de VAD não prevista'!G2 -> 0.0021231423 | K12: ='%Incidencia de VAD não prevista'!H2 -> 0 | L12: ='%Incidencia de VAD não prevista'!I2 -> 0 | M12: ='%Incidencia de VAD não prevista'!J2 -> 0.0056390977 | N12: ='%Incidencia de VAD não prevista'!K2 -> 0.0055350554 | R12: ='%Incidencia de VAD não prevista'!O2 -> 0
A13: 12 | B13: Resultado | C13: Efetividade clínica | D13: ='% Incidência de NVPO'!A2 -> TAXA DE INCIDÊNCIA DE NÁUSEA E VÔMITO NO PERÍODO INTRAOPERATÓRIO ATÉ A ALTA ANESTÉSICA | E13: ≤20% global; ≤30% em alto risco (Apfel≥3) | F13: ='% Incidência de NVPO'!C2 -> 0.051843318 | G13: ='% Incidência de NVPO'!D2 -> 0.058378378 | H13: ='% Incidência de NVPO'!E2 -> 0.063321386 | I13: ='% Incidência de NVPO'!F2 -> 0.045263158 | J13: ='% Incidência de NVPO'!G2 -> 0.064189189 | K13: ='% Incidência de NVPO'!H2 -> 0.054466231 | L13: ='% Incidência de NVPO'!I2 -> 0.058341863 | M13: ='% Incidência de NVPO'!J2 -> 0.052465897 | N13: ='% Incidência de NVPO'!K2 -> 0.039274924 | R13: ='% Incidência de NVPO'!O2 -> 0.054466231
A14: 13 | B14: Processo | C14: Segurança do paciente | D14: ='%Efetiv. no manejo de Int. Anes'!A1 -> EFETIVIDADE DO PROTOCOLO DE MANEJO DE INTOXICAÇÃO POR ANESTÉSICOS LOCAIS | E14: ≥90% | F14: ='%Efetiv. no manejo de Int. Anes'!C2 -> 1 | G14: ='%Efetiv. no manejo de Int. Anes'!D2 -> 1 | H14: ='%Efetiv. no manejo de Int. Anes'!E2 -> 1 | I14: ='%Efetiv. no manejo de Int. Anes'!F2 -> 1 | J14: ='%Efetiv. no manejo de Int. Anes'!G2 -> 1 | K14: ='%Efetiv. no manejo de Int. Anes'!H2 -> 1 | L14: ='%Efetiv. no manejo de Int. Anes'!I2 -> 1 | M14: ='%Efetiv. no manejo de Int. Anes'!J2 -> 1 | N14: ='%Efetiv. no manejo de Int. Anes'!K2 -> 1 | R14: ='%Efetiv. no manejo de Int. Anes'!O2 -> 1
A15: 13 | B15: Processo | C15: Segurança do paciente | D15: TAXA DE ADESÃO A ANTIBIOTICOPROFILAXIA ATÉ 60 MINT ANTES DA INCISÃO | E15: ≥95% | F15: 0.99 | G15: 0.99 | H15: 0.98 | I15: 0.91 | J15: 0.87 | K15: 0.85 | L15: 0.94 | M15: 0.96 | N15: 0.97
D16: TAXA DE ADESÃO A ANTIBIOTICOPROFILAXIA DROGA CORRETA | E16: ≥95% | K16: 1 | L16: 1 | M16: 1 | N16: 1
D17: TAXA DE ADESÃO A ANTIBIOTICOPROFILAXIA REPIQUE | E17: ≥95% | K17: 1 | L17: 1 | M17: 1 | N17: 1
A18: 13 | B18: Processo | C18: Segurança do paciente | D18: ='% Conformidade do ATB'!A1 -> TAXA DE CONFORMIDADE DA PROFILAXIA ANTIMICROBIANA CIRÚRGICA DURANTE O PROCEDIMENTO | E18: ≥95% | F18: =MEDIAN(F15:F17) -> 0.99 | G18: =MEDIAN(G15:G17) -> 0.99 | H18: =MEDIAN(H15:H17) -> 0.98 | I18: =MEDIAN(I15:I17) -> 0.91 | J18: =MEDIAN(J15:J17) -> 0.87 | K18: 0.95 | L18: 0.98 | M18: =MEDIAN(M15:M17) -> 1 | N18: =MEDIAN(N15:N17) -> 1 | R18: ='% Conformidade do ATB'!O2 -> 0.89
A19: 13 | B19: Processo | C19: Efetividade clínica | D19: ='% Efet. Prevenção Cefaléia PPD'!A1 -> EFETIVIDADE DO PROTOCOLO DE PREVENÇÃO DE CAFALÉIA PÓS PUNÇÃO DURAL | E19: ≥95% de uso conforme protocolo; incidência CPPD <1% (não obstétrica) <3% obstétrica | F19: ='% Efet. Prevenção Cefaléia PPD'!C2 -> 1 | G19: ='% Efet. Prevenção Cefaléia PPD'!D2 -> 1 | H19: ='% Efet. Prevenção Cefaléia PPD'!E2 -> 1 | I19: ='% Efet. Prevenção Cefaléia PPD'!F2 -> 1 | J19: ='% Efet. Prevenção Cefaléia PPD'!G2 -> 0.99 | K19: ='% Efet. Prevenção Cefaléia PPD'!H2 -> 1 | L19: ='% Efet. Prevenção Cefaléia PPD'!I2 -> 0.97 | M19: ='% Efet. Prevenção Cefaléia PPD'!J2 -> 0.99 | N19: ='% Efet. Prevenção Cefaléia PPD'!K2 -> 1 | R19: ='% Efet. Prevenção Cefaléia PPD'!O2 -> 1
A20: 13 | B20: Resultado | C20: Efetividade clínica | D20: ='% Incidência de Hipotermia'!A1 -> TAXA DE INCIDÊNCIA DE HIPOTERMIA NÃO INTENCIONAL NO PERÍODO INTRAOPERATÓRIO ATÉ A ALTA ANESTÉSICA | E20: ≤5% ≥90% com T° ≥ 36 °C no fim da anestesia | F20: ='% Incidência de Hipotermia'!C2 -> 0.004076087 | G20: ='% Incidência de Hipotermia'!D2 -> 0.0045602606 | H20: ='% Incidência de Hipotermia'!E2 -> 0.0019569472 | I20: ='% Incidência de Hipotermia'!F2 -> 0.0024660912 | J20: ='% Incidência de Hipotermia'!G2 -> 0.0024891101 | K20: ='% Incidência de Hipotermia'!H2 -> 0.0032679739 | L20: ='% Incidência de Hipotermia'!I2 -> 0.0022459293 | M20: ='% Incidência de Hipotermia'!J2 -> 0.0034883721 | N20: ='% Incidência de Hipotermia'!K2 -> 0.0049369172 | R20: ='% Incidência de Hipotermia'!O2 -> 0.0032679739
A21: 13 | B21: Resultado | C21: Segurança do paciente | D21: TAXA DE ADESÃO AOS PROTOCOLOS SEGURANÇA | E21: 95% de adesão aos protocolos padronizados até o final de 2025. | F21: ='% adesão aos prot.segurança'!C2 -> 0.91331178 | G21: ='% adesão aos prot.segurança'!D2 -> 0.91440559 | H21: ='% adesão aos prot.segurança'!E2 -> 0.92696321 | I21: ='% adesão aos prot.segurança'!F2 -> 0.90945573 | J21: ='% adesão aos prot.segurança'!G2 -> 0.92497482 | K21: ='% adesão aos prot.segurança'!H2 -> 0.91330698 | L21: ='% adesão aos prot.segurança'!I2 -> 0.94478528 | M21: ='% adesão aos prot.segurança'!J2 -> 0.94006934 | N21: ='% adesão aos prot.segurança'!K2 -> 0.93551469 | R21: =MEDIAN(F21:Q21) -> 0.92497482
A22: 13 | B22: Processo | C22: Efetividade clínica | D22: TAXA DE ADESÃO AOS PROTOCOLOS CLÍNICOS-ASSISTENCIAIS | E22: 95% de adesão aos protocolos padronizados até o final de 2025. | F22: ='% adesão aos prot clinico Assit'!C2 -> 0.82763115 | G22: ='% adesão aos prot clinico Assit'!D2 -> 0.83924647 | H22: ='% adesão aos prot clinico Assit'!E2 -> 0.82133006 | I22: ='% adesão aos prot clinico Assit'!F2 -> 0.84570766 | J22: ='% adesão aos prot clinico Assit'!G2 -> 0.80821513 | K22: ='% adesão aos prot clinico Assit'!H2 -> 0.82384342 | L22: ='% adesão aos prot clinico Assit'!I2 -> 0.84368009 | M22: ='% adesão aos prot clinico Assit'!J2 -> 0.83897605 | N22: ='% adesão aos prot clinico Assit'!K2 -> 0.8411389 | R22: =MEDIAN(F22:Q22) -> 0.83897605
A23: 13 | B23: Estrutura | C23: Aprendizado / Capacitação | D23: TAXA DE PROFISSIONAIS TREINADOS | E23: Atingir 80% em 2025
A24: 13 | B24: Resultado | C24: Cliente / Satisfação | D24: NPS (NET PROMOTER SCORE) ÍNDICE DE SATISFAÇÃO DOS CLIENTES | E24: ≥ 8,5 pontos | F24: 9.81 | G24: 10 | H24: 9.62 | I24: 9.54 | J24: 9.75 | K24: 9.79 | L24: 9.67 | M24: 9.65 | R24: =MEDIAN(F24:Q24) -> 9.71
A25: 13 | B25: Resultado | C25: Cliente / Imagem e reputação | D25: INDICE DE PERCEPÇÃO DE VALOR DOS CLIENTES | E25: > 4,5 Experiência Geral do Cliente | F25: 4.87 | G25: 4.79 | H25: 4.81 | I25: 4.76 | J25: 4.94 | K25: 4.92 | L25: 4.91 | M25: 4.89 | R25: =MEDIAN(F25:Q25) -> 4.88
A26: 13 | B26: Resultado | C26: Financeiro / Sustentabilidade | D26: LUCRO LIQUIDO | E26: Manter resultado positivo anual
A27: 13 | B27: Estrutura | C27: Financeiro / Eficiência econômica | D27: MARGEM LIQUIDA | E27: ≥10%
A28: 13 | B28: Estrutura | C28: Financeiro / Crescimento | D28: RECEITA BRUTA | E28: Aumentar ≥5% vs ano anterior
A29: 13 | B29: Estrutura | C29: Financeiro / Controle de custos | D29: PARTICIPAÇÃO DOS CUSTOS FIXOS | E29: ≤50%

Sheet Planilha1
B1: Classificação (Donabedian) | C1: Tipo Funcional | D1: INDICADOR | E1: META ESTABELECIDA | F1: Janeiro | G1: Fevereiro | H1: Março | I1: Abril | J1: Maio | K1: Junho | L1: Julho | M1: Agosto | N1: Setembro | O1: Média Anual
A2: 1 | B2: Processo | C2: Efetividade clínica | D2: ='% Consulta pré anestésica'!A2 -> TAXA DE PROCEDIMENTOS ELETIVOS COM CONSULTA PRÉ-ANESTÉSICA AMBULATORIAL | E2: ≥95% | F2: ='% Consulta pré anestésica'!C2 -> 0.79517191 | G2: ='% Consulta pré anestésica'!D2 -> 0.79330007 | H2: ='% Consulta pré anestésica'!E2 -> 0.75690236 | I2: ='% Consulta pré anestésica'!F2 -> 0.84649123 | J2: ='% Consulta pré anestésica'!G2 -> 0.85654513 | K2: ='% Consulta pré anestésica'!H2 -> 0.96018277 | L2: ='% Consulta pré anestésica'!I2 -> 0.95281996 | M2: ='% Consulta pré anestésica'!J2 -> 0.97834758 | N2: ='% Consulta pré anestésica'!K2 -> 0.97022198 | O2: ='% Consulta pré anestésica'!O2 -> 0.85654513
A3: 2 | B3: Resultado | C3: Efetividade clínica | D3: ='% Incidencia de dor aguda'!A1 -> INCIDÊNCIA DE DOR AGUDA NO PERÍODO INTRAOPERATÓRIO ATÉ A ALTA ANESTÉSICA | E3: ≤10% | F3: ='% Incidencia de dor aguda'!C2 -> 0.050951087 | G3: ='% Incidencia de dor aguda'!D2 -> 0.043648208 | H3: ='% Incidencia de dor aguda'!E2 -> 0.040443575 | I3: ='% Incidencia de dor aguda'!F2 -> 0.034525277 | J3: ='% Incidencia de dor aguda'!G2 -> 0.059738643 | K3: ='% Incidencia de dor aguda'!H2 -> 0.033333333 | L3: ='% Incidencia de dor aguda'!I2 -> 0.035934868 | M3: ='% Incidencia de dor aguda'!J2 -> 0.03372093 | N3: ='% Incidencia de dor aguda'!K2 -> 0.036752606 | O3: ='% Incidencia de dor aguda'!O2 -> 0.036752606
A4: 3 | B4: Processo | C4: Efetividade clínica | D4: ='% Abreviação do jejum P.'!A1 -> INCIDÊNCIA DE ABREVIAÇÃO DO JEJUM PROLONGADO | E4: ≥60% | F4: ='% Abreviação do jejum P.'!C2 -> 0.32 | G4: ='% Abreviação do jejum P.'!D2 -> 0.35 | H4: ='% Abreviação do jejum P.'!E2 -> 0.32 | I4: ='% Abreviação do jejum P.'!F2 -> 0.41 | J4: ='% Abreviação do jejum P.'!G2 -> 0.38 | K4: ='% Abreviação do jejum P.'!H2 -> 0.4 | L4: ='% Abreviação do jejum P.'!I2 -> 0.4 | M4: ='% Abreviação do jejum P.'!J2 -> 0.43 | N4: ='% Abreviação do jejum P.'!K2 -> 0.42 | O4: ='% Abreviação do jejum P.'!O2 -> 0.4
A5: 4 | B5: Resultado | C5: Segurança do paciente | D5: ='Incidencia de PCR até a Alta'!A1 -> INCIDÊNCIA DE PARADA CARDIORRESPIRATÓRIA NO PERÍODO DA INDUÇÃO ATÉ A ALTA ANESTÉSICA | E5: Meta zero / ≤1/10.000 anestesias | F5: ='Incidencia de PCR até a Alta'!C2 -> 0 | G5: ='Incidencia de PCR até a Alta'!D2 -> 0 | H5: ='Incidencia de PCR até a Alta'!E2 -> 0 | I5: ='Incidencia de PCR até a Alta'!F2 -> 0 | J5: ='Incidencia de PCR até a Alta'!G2 -> 0 | K5: ='Incidencia de PCR até a Alta'!H2 -> 0 | L5: ='Incidencia de PCR até a Alta'!I2 -> 0 | M5: ='Incidencia de PCR até a Alta'!J2 -> 0.00058139535 | N5: ='Incidencia de PCR até a Alta'!K2 -> 0.00054854635 | O5: ='Incidencia de PCR até a Alta'!O2 -> 0
A6: 5 | B6: Processo | C6: Efetividade clínica | D6: ='% Mudança da Tecnica Anestésica'!A1 -> TAXA DE MUDANÇA DE TÉCNICA ANESTÉSICA | E6: <5% | F6: ='% Mudança da Tecnica Anestésica'!C2 -> 0 | G6: ='% Mudança da Tecnica Anestésica'!D2 -> 0 | H6: ='% Mudança da Tecnica Anestésica'!E2 -> 0 | I6: ='% Mudança da Tecnica Anestésica'!F2 -> 0 | J6: ='% Mudança da Tecnica Anestésica'!G2 -> 0 | K6: ='% Mudança da Tecnica Anestésica'!H2 -> 0 | L6: ='% Mudança da Tecnica Anestésica'!I2 -> 0 | M6: ='% Mudança da Tecnica Anestésica'!J2 -> 0 | N6: ='% Mudança da Tecnica Anestésica'!K2 -> 0.001 | O6: ='% Mudança da Tecnica Anestésica'!O2 -> 0
A7: 6 | B7: Resultado | C7: Segurança do paciente | D7: ='% Incidência Enc. UTI'!A2 -> INCIDÊNCIA DE PACIENTES ENCAMINHADOS PARA UTI SEM PLANEJAMENTO PRÉVIO COM INDICAÇÃO DECORRENTE DE EVENTOS ANESTÉSICOS | E7: Meta zero / ≤0,3% | F7: ='% Incidência Enc. UTI'!C2 -> 0.00071428571 | G7: ='% Incidência Enc. UTI'!D2 -> 0 | H7: ='% Incidência Enc. UTI'!E2 -> 0.00066622252 | I7: ='% Incidência Enc. UTI'!F2 -> 0.00062460962 | J7: ='% Incidência Enc. UTI'!G2 -> 0.0023837902 | K7: ='% Incidência Enc. UTI'!H2 -> 0.0012903226 | L7: ='% Incidência Enc. UTI'!I2 -> 0.0021401819 | M7: ='% Incidência Enc. UTI'!J2 -> 0.0011267606 | N7: ='% Incidência Enc. UTI'!K2 -> 0.0010723861 | O7: ='% Incidência Enc. UTI'!O2 -> 0.0010723861
A8: 7 | B8: Processo | C8: Efetividade clínica | D8: ='% Efet. no controle glicemico'!A2 -> EFETIVIDADE DO PROTOCOLO DE CONTROLE GLICÊMICO NO PERÍODO PERIOPERATÓRIO | E8: ≥90% | F8: ='% Efet. no controle glicemico'!C2 -> 0.74 | G8: ='% Efet. no controle glicemico'!D2 -> 0.76 | H8: ='% Efet. no controle glicemico'!E2 -> 0.78 | I8: ='% Efet. no controle glicemico'!F2 -> 0.72 | J8: ='% Efet. no controle glicemico'!G2 -> 0.8 | K8: ='% Efet. no controle glicemico'!H2 -> 0.77 | L8: ='% Efet. no controle glicemico'!I2 -> 0.91 | M8: ='% Efet. no controle glicemico'!J2 -> 0.83878241 | N8: ='% Efet. no controle glicemico'!K2 -> 0.82442748 | O8: ='% Efet. no controle glicemico'!O2 -> 0.78
A9: 8 | B9: Resultado | C9: Segurança do paciente | D9: ='% Saídas sem eventos anestésico'!A2 -> SAÍDAS SEM EVENTOS RELACIONADOS AO ATO ANESTÉSICO | E9: >90% | F9: ='% Saídas sem eventos anestésico'!C2 -> 0.86 | G9: ='% Saídas sem eventos anestésico'!D2 -> 0.86 | H9: ='% Saídas sem eventos anestésico'!E2 -> 0.87 | I9: ='% Saídas sem eventos anestésico'!F2 -> 0.89 | J9: ='% Saídas sem eventos anestésico'!G2 -> 0.84 | K9: ='% Saídas sem eventos anestésico'!H2 -> 0.88 | L9: ='% Saídas sem eventos anestésico'!I2 -> 0.88 | M9: ='% Saídas sem eventos anestésico'!J2 -> 0.88 | N9: ='% Saídas sem eventos anestésico'!K2 -> 0.9 | O9: ='% Saídas sem eventos anestésico'!O2 -> 0.88
A10: 9 | B10: Resultado | C10: Segurança do paciente | D10: ='% Mortalidade Associada a anest'!A2 -> MORTALIDADE ASSOCIADA A ANESTESIA EM 48 HORAS E ATÉ 30 DIAS | E10: Meta zero / ≤1/100.000 em 48h e ≤5/100.000 em 30d | F10: ='% Mortalidade Associada a anest'!C2 -> 0 | G10: ='% Mortalidade Associada a anest'!D2 -> 0 | H10: ='% Mortalidade Associada a anest'!E2 -> 0 | I10: ='% Mortalidade Associada a anest'!F2 -> 0 | J10: ='% Mortalidade Associada a anest'!G2 -> 0 | K10: ='% Mortalidade Associada a anest'!H2 -> 0 | L10: ='% Mortalidade Associada a anest'!I2 -> 0.001 | M10: ='% Mortalidade Associada a anest'!J2 -> 0 | N10: ='% Mortalidade Associada a anest'!K2 -> 0 | O10: ='% Mortalidade Associada a anest'!O2 -> 0
A11: 10 | B11: Processo | C11: Efetividade clínica | D11: ='% Estratificação de risco'!A2 -> TAXA DE ESTRATIFICAÇÃO DE RISCO ANESTÉSICO DO SERVIÇO | E11: ≥98–100% | F11: ='% Estratificação de risco'!C2 -> 1 | G11: ='% Estratificação de risco'!D2 -> 1 | H11: ='% Estratificação de risco'!E2 -> 1 | I11: ='% Estratificação de risco'!F2 -> 1 | J11: ='% Estratificação de risco'!G2 -> 1 | K11: ='% Estratificação de risco'!H2 -> 1 | L11: ='% Estratificação de risco'!I2 -> 1 | M11: ='% Estratificação de risco'!J2 -> 1 | N11: ='% Estratificação de risco'!K2 -> 1 | O11: ='% Estratificação de risco'!O2 -> 1
A12: 11 | B12: Resultado | C12: Segurança do paciente | D12: ='%Incidencia de VAD não prevista'!A2 -> INCIDÊNCIA DE VIA ÁREA DIFÍCIL NÃO IDENTIFICADA NO PERÍODO INTRAOPERATÓRIO | E12: ≤2% | F12: ='%Incidencia de VAD não prevista'!C2 -> 0 | G12: ='%Incidencia de VAD não prevista'!D2 -> 0 | H12: ='%Incidencia de VAD não prevista'!E2 -> 0 | I12: ='%Incidencia de VAD não prevista'!F2 -> 0 | J12: ='%Incidencia de VAD não prevista'!G2 -> 0.0021231423 | K12: ='%Incidencia de VAD não prevista'!H2 -> 0 | L12: ='%Incidencia de VAD não prevista'!I2 -> 0 | M12: ='%Incidencia de VAD não prevista'!J2 -> 0.0056390977 | N12: ='%Incidencia de VAD não prevista'!K2 -> 0.0055350554 | O12: ='%Incidencia de VAD não prevista'!O2 -> 0
A13: 12 | B13: Resultado | C13: Efetividade clínica | D13: ='% Incidência de NVPO'!A2 -> TAXA DE INCIDÊNCIA DE NÁUSEA E VÔMITO NO PERÍODO INTRAOPERATÓRIO ATÉ A ALTA ANESTÉSICA | E13: ≤20% global; ≤30% em alto risco (Apfel≥3) | F13: ='% Incidência de NVPO'!C2 -> 0.051843318 | G13: ='% Incidência de NVPO'!D2 -> 0.058378378 | H13: ='% Incidência de NVPO'!E2 -> 0.063321386 | I13: ='% Incidência de NVPO'!F2 -> 0.045263158 | J13: ='% Incidência de NVPO'!G2 -> 0.064189189 | K13: ='% Incidência de NVPO'!H2 -> 0.054466231 | L13: ='% Incidência de NVPO'!I2 -> 0.058341863 | M13: ='% Incidência de NVPO'!J2 -> 0.052465897 | N13: ='% Incidência de NVPO'!K2 -> 0.039274924 | O13: ='% Incidência de NVPO'!O2 -> 0.054466231
A14: 13 | B14: Processo | C14: Segurança do paciente | D14: ='%Efetiv. no manejo de Int. Anes'!A1 -> EFETIVIDADE DO PROTOCOLO DE MANEJO DE INTOXICAÇÃO POR ANESTÉSICOS LOCAIS | E14: ≥90% | F14: ='%Efetiv. no manejo de Int. Anes'!C2 -> 1 | G14: ='%Efetiv. no manejo de Int. Anes'!D2 -> 1 | H14: ='%Efetiv. no manejo de Int. Anes'!E2 -> 1 | I14: ='%Efetiv. no manejo de Int. Anes'!F2 -> 1 | J14: ='%Efetiv. no manejo de Int. Anes'!G2 -> 1 | K14: ='%Efetiv. no manejo de Int. Anes'!H2 -> 1 | L14: ='%Efetiv. no manejo de Int. Anes'!I2 -> 1 | M14: ='%Efetiv. no manejo de Int. Anes'!J2 -> 1 | N14: ='%Efetiv. no manejo de Int. Anes'!K2 -> 1 | O14: ='%Efetiv. no manejo de Int. Anes'!O2 -> 1
A15: 13 | B15: Processo | C15: Segurança do paciente | D15: TAXA DE ADESÃO A ANTIBIOTICOPROFILAXIA ATÉ 60 MINT ANTES DA INCISÃO | E15: ≥95% | F15: 0.99 | G15: 0.99 | H15: 0.98 | I15: 0.91 | J15: 0.87 | K15: 0.85 | L15: 0.94 | M15: 0.96 | N15: 0.97
D16: TAXA DE ADESÃO A ANTIBIOTICOPROFILAXIA DROGA CORRETA | E16: ≥95% | K16: 1 | L16: 1 | M16: 1 | N16: 1
D17: TAXA DE ADESÃO A ANTIBIOTICOPROFILAXIA REPIQUE | E17: ≥95% | K17: 1 | L17: 1 | M17: 1 | N17: 1
A18: 13 | B18: Processo | C18: Segurança do paciente | D18: ='% Conformidade do ATB'!A1 -> TAXA DE CONFORMIDADE DA PROFILAXIA ANTIMICROBIANA CIRÚRGICA DURANTE O PROCEDIMENTO | E18: ≥95% | F18: =MEDIAN(F15:F17) -> 0.99 | G18: =MEDIAN(G15:G17) -> 0.99 | H18: =MEDIAN(H15:H17) -> 0.98 | I18: =MEDIAN(I15:I17) -> 0.91 | J18: =MEDIAN(J15:J17) -> 0.87 | K18: 0.95 | L18: 0.98 | M18: =MEDIAN(M15:M17) -> 1 | N18: =MEDIAN(N15:N17) -> 1 | O18: ='% Conformidade do ATB'!O2 -> 0.89
A19: 13 | B19: Processo | C19: Efetividade clínica | D19: ='% Efet. Prevenção Cefaléia PPD'!A1 -> EFETIVIDADE DO PROTOCOLO DE PREVENÇÃO DE CAFALÉIA PÓS PUNÇÃO DURAL | E19: ≥95% de uso conforme protocolo; incidência CPPD <1% (não obstétrica) <3% obstétrica | F19: ='% Efet. Prevenção Cefaléia PPD'!C2 -> 1 | G19: ='% Efet. Prevenção Cefaléia PPD'!D2 -> 1 | H19: ='% Efet. Prevenção Cefaléia PPD'!E2 -> 1 | I19: ='% Efet. Prevenção Cefaléia PPD'!F2 -> 1 | J19: ='% Efet. Prevenção Cefaléia PPD'!G2 -> 0.99 | K19: ='% Efet. Prevenção Cefaléia PPD'!H2 -> 1 | L19: ='% Efet. Prevenção Cefaléia PPD'!I2 -> 0.97 | M19: ='% Efet. Prevenção Cefaléia PPD'!J2 -> 0.99 | N19: ='% Efet. Prevenção Cefaléia PPD'!K2 -> 1 | O19: ='% Efet. Prevenção Cefaléia PPD'!O2 -> 1
A20: 13 | B20: Resultado | C20: Efetividade clínica | D20: ='% Incidência de Hipotermia'!A1 -> TAXA DE INCIDÊNCIA DE HIPOTERMIA NÃO INTENCIONAL NO PERÍODO INTRAOPERATÓRIO ATÉ A ALTA ANESTÉSICA | E20: ≤5% ≥90% com T° ≥ 36 °C no fim da anestesia | F20: ='% Incidência de Hipotermia'!C2 -> 0.004076087 | G20: ='% Incidência de Hipotermia'!D2 -> 0.0045602606 | H20: ='% Incidência de Hipotermia'!E2 -> 0.0019569472 | I20: ='% Incidência de Hipotermia'!F2 -> 0.0024660912 | J20: ='% Incidência de Hipotermia'!G2 -> 0.0024891101 | K20: ='% Incidência de Hipotermia'!H2 -> 0.0032679739 | L20: ='% Incidência de Hipotermia'!I2 -> 0.0022459293 | M20: ='% Incidência de Hipotermia'!J2 -> 0.0034883721 | N20: ='% Incidência de Hipotermia'!K2 -> 0.0049369172 | O20: ='% Incidência de Hipotermia'!O2 -> 0.0032679739
A21: 13 | B21: Resultado | C21: Segurança do paciente | D21: TAXA DE ADESÃO AOS PROTOCOLOS SEGURANÇA | E21: 95% de adesão aos protocolos padronizados até o final de 2025. | F21: ='% adesão aos prot.segurança'!C2 -> 0.91331178 | G21: ='% adesão aos prot.segurança'!D2 -> 0.91440559 | H21: ='% adesão aos prot.segurança'!E2 -> 0.92696321 | I21: ='% adesão aos prot.segurança'!F2 -> 0.90945573 | J21: ='% adesão aos prot.segurança'!G2 -> 0.92497482 | K21: ='% adesão aos prot.segurança'!H2 -> 0.91330698 | L21: ='% adesão aos prot.segurança'!I2 -> 0.94478528 | M21: ='% adesão aos prot.segurança'!J2 -> 0.94006934 | N21: ='% adesão aos prot.segurança'!K2 -> 0.93551469 | O21: =MEDIAN(F21:N21) -> 0.92497482
A22: 13 | B22: Processo | C22: Efetividade clínica | D22: TAXA DE ADESÃO AOS PROTOCOLOS CLÍNICOS-ASSISTENCIAIS | E22: 95% de adesão aos protocolos padronizados até o final de 2025. | F22: ='% adesão aos prot clinico Assit'!C2 -> 0.82763115 | G22: ='% adesão aos prot clinico Assit'!D2 -> 0.83924647 | H22: ='% adesão aos prot clinico Assit'!E2 -> 0.82133006 | I22: ='% adesão aos prot clinico Assit'!F2 -> 0.84570766 | J22: ='% adesão aos prot clinico Assit'!G2 -> 0.80821513 | K22: ='% adesão aos prot clinico Assit'!H2 -> 0.82384342 | L22: ='% adesão aos prot clinico Assit'!I2 -> 0.84368009 | M22: ='% adesão aos prot clinico Assit'!J2 -> 0.83897605 | N22: ='% adesão aos prot clinico Assit'!K2 -> 0.8411389 | O22: =MEDIAN(F22:N22) -> 0.83897605
A23: 13 | B23: Estrutura | C23: Aprendizado / Capacitação | D23: TAXA DE PROFISSIONAIS TREINADOS | E23: Atingir 80% em 2025
A24: 13 | B24: Resultado | C24: Cliente / Satisfação | D24: NPS (NET PROMOTER SCORE) ÍNDICE DE SATISFAÇÃO DOS CLIENTES | E24: ≥ 8,5 pontos | F24: 9.81 | G24: 10 | H24: 9.62 | I24: 9.54 | J24: 9.75 | K24: 9.79 | L24: 9.67 | M24: 9.65 | O24: =MEDIAN(F24:N24) -> 9.71
A25: 13 | B25: Resultado | C25: Cliente / Imagem e reputação | D25: INDICE DE PERCEPÇÃO DE VALOR DOS CLIENTES | E25: > 4,5 Experiência Geral do Cliente | F25: 4.87 | G25: 4.79 | H25: 4.81 | I25: 4.76 | J25: 4.94 | K25: 4.92 | L25: 4.91 | M25: 4.89 | O25: =MEDIAN(F25:N25) -> 4.88

Sheet Planilha2
B1: Classificação (Donabedian) | C1: Tipo Funcional | D1: INDICADOR | E1: META ESTABELECIDA | F1: Julho | G1: Agosto | H1: Setembro | I1: Média Anual
A2: 1 | B2: Processo | C2: Efetividade clínica | D2: TAXA DE PROCEDIMENTOS ELETIVOS COM CONSULTA PRÉ-ANESTÉSICA AMBULATORIAL | E2: ≥95% | F2: 0.95281996 | G2: 0.97834758 | H2: 0.97022198 | I2: 0.85654513
A3: 2 | B3: Resultado | C3: Efetividade clínica | D3: INCIDÊNCIA DE DOR AGUDA NO PERÍODO INTRAOPERATÓRIO ATÉ A ALTA ANESTÉSICA | E3: ≤10% | F3: 0.035934868 | G3: 0.03372093 | H3: 0.036752606 | I3: 0.036752606
A4: 3 | B4: Processo | C4: Efetividade clínica | D4: INCIDÊNCIA DE ABREVIAÇÃO DO JEJUM PROLONGADO | E4: ≥60% | F4: 0.4 | G4: 0.43 | H4: 0.42 | I4: 0.4
A5: 4 | B5: Resultado | C5: Segurança do paciente | D5: INCIDÊNCIA DE PARADA CARDIORRESPIRATÓRIA NO PERÍODO DA INDUÇÃO ATÉ A ALTA ANESTÉSICA | E5: Meta zero / ≤1/10.000 anestesias | F5: 0 | G5: 0.00058139535 | H5: 0.00054854635 | I5: 0
A6: 5 | B6: Processo | C6: Efetividade clínica | D6: TAXA DE MUDANÇA DE TÉCNICA ANESTÉSICA | E6: <5% | F6: 0 | G6: 0 | H6: 0.001 | I6: 0
A7: 6 | B7: Resultado | C7: Segurança do paciente | D7: INCIDÊNCIA DE PACIENTES ENCAMINHADOS PARA UTI SEM PLANEJAMENTO PRÉVIO COM INDICAÇÃO DECORRENTE DE EVENTOS ANESTÉSICOS | E7: Meta zero / ≤0,3% | F7: 0.0021401819 | G7: 0.0011267606 | H7: 0.0010723861 | I7: 0.0010723861
A8: 7 | B8: Processo | C8: Efetividade clínica | D8: EFETIVIDADE DO PROTOCOLO DE CONTROLE GLICÊMICO NO PERÍODO PERIOPERATÓRIO | E8: ≥90% | F8: 0.91 | G8: 0.83878241 | H8: 0.82442748 | I8: 0.78
A9: 8 | B9: Resultado | C9: Segurança do paciente | D9: SAÍDAS SEM EVENTOS RELACIONADOS AO ATO ANESTÉSICO | E9: >90% | F9: 0.88 | G9: 0.88 | H9: 0.9 | I9: 0.88
A10: 9 | B10: Resultado | C10: Segurança do paciente | D10: MORTALIDADE ASSOCIADA A ANESTESIA EM 48 HORAS E ATÉ 30 DIAS | E10: Meta zero / ≤1/100.000 em 48h e ≤5/100.000 em 30d | F10: 0.001 | G10: 0 | H10: 0 | I10: 0
A11: 10 | B11: Processo | C11: Efetividade clínica | D11: TAXA DE ESTRATIFICAÇÃO DE RISCO ANESTÉSICO DO SERVIÇO | E11: ≥98–100% | F11: 1 | G11: 1 | H11: 1 | I11: 1
A12: 11 | B12: Resultado | C12: Segurança do paciente | D12: INCIDÊNCIA DE VIA ÁREA DIFÍCIL NÃO IDENTIFICADA NO PERÍODO INTRAOPERATÓRIO | E12: ≤2% | F12: 0 | G12: 0.0056390977 | H12: 0.0055350554 | I12: 0
A13: 12 | B13: Resultado | C13: Efetividade clínica | D13: TAXA DE INCIDÊNCIA DE NÁUSEA E VÔMITO NO PERÍODO INTRAOPERATÓRIO ATÉ A ALTA ANESTÉSICA | E13: ≤20% global; ≤30% em alto risco (Apfel≥3) | F13: 0.058341863 | G13: 0.052465897 | H13: 0.039274924 | I13: 0.054466231
A14: 13 | B14: Processo | C14: Segurança do paciente | D14: EFETIVIDADE DO PROTOCOLO DE MANEJO DE INTOXICAÇÃO POR ANESTÉSICOS LOCAIS | E14: ≥90% | F14: 1 | G14: 1 | H14: 1 | I14: 1
A15: 13 | B15: Processo | C15: Segurança do paciente | D15: TAXA DE ADESÃO A ANTIBIOTICOPROFILAXIA ATÉ 60 MINT ANTES DA INCISÃO | E15: ≥95% | F15: 0.94 | G15: 0.96 | H15: 0.97
D16: TAXA DE ADESÃO A ANTIBIOTICOPROFILAXIA DROGA CORRETA | E16: ≥95% | F16: 1 | G16: 1 | H16: 1
D17: TAXA DE ADESÃO A ANTIBIOTICOPROFILAXIA REPIQUE | E17: ≥95% | F17: 1 | G17: 1 | H17: 1
A18: 13 | B18: Processo | C18: Segurança do paciente | D18: TAXA DE CONFORMIDADE DA PROFILAXIA ANTIMICROBIANA CIRÚRGICA DURANTE O PROCEDIMENTO | E18: ≥95% | F18: 0.98 | G18: 1 | H18: 1 | I18: 0.89
A19: 13 | B19: Processo | C19: Efetividade clínica | D19: EFETIVIDADE DO PROTOCOLO DE PREVENÇÃO DE CAFALÉIA PÓS PUNÇÃO DURAL | E19: ≥95% de uso conforme protocolo; incidência CPPD <1% (não obstétrica) <3% obstétrica | F19: 0.97 | G19: 0.99 | H19: 1 | I19: 1
A20: 13 | B20: Resultado | C20: Efetividade clínica | D20: TAXA DE INCIDÊNCIA DE HIPOTERMIA NÃO INTENCIONAL NO PERÍODO INTRAOPERATÓRIO ATÉ A ALTA ANESTÉSICA | E20: ≤5% ≥90% com T° ≥ 36 °C no fim da anestesia | F20: 0.0022459293 | G20: 0.0034883721 | H20: 0.0049369172 | I20: 0.0032679739
A21: 13 | B21: Resultado | C21: Segurança do paciente | D21: TAXA DE ADESÃO AOS PROTOCOLOS SEGURANÇA | E21: 95% de adesão aos protocolos padronizados até o final de 2025. | F21: 0.94478528 | G21: 0.94006934 | H21: 0.93551469 | I21: 0.92497482
A22: 13 | B22: Processo | C22: Efetividade clínica | D22: TAXA DE ADESÃO AOS PROTOCOLOS CLÍNICOS-ASSISTENCIAIS | E22: 95% de adesão aos protocolos padronizados até o final de 2025. | F22: 0.84368009 | G22: 0.83897605 | H22: 0.8411389 | I22: 0.83897605

Sheet Metas recomendadas
A1: Indicador | B1: Meta recomendada | C1: Fundamentação / Referência principal
A2: Taxa de procedimentos eletivos com consulta pré-anestésica ambulatorial | B2: ≥ 95% | C2: Diretrizes ASA; reduz cancelamentos e eventos adversos
A3: Incidência de dor aguda no período intraoperatório até a alta anestésica | B3: ≤ 10% (global) / ≤ 5% (ERAS) | C3: ASPAN, ASA – controle multimodal da dor
A4: Incidência de abreviação do jejum prolongado | B4: ≤10% de não conformidade (≥90% de aderência) | C4: Diretrizes ASA 2023 / Projeto ACERTO / ERAS
A5: Incidência de parada cardiorrespiratória da indução até a alta anestésica | B5: Meta zero; vigilância ≤ 1/10.000 | C5: ANZCA, ASA Closed Claims
A6: Taxa de mudança de técnica anestésica | B6: ≤ 5% | C6: Benchmark operacional; falha técnica = evento rastreável
A7: Incidência de pacientes encaminhados para UTI sem planejamento prévio por evento anestésico | B7: Meta zero; referência ≤ 0,3% | C7: Estudos observacionais multicêntricos (ANZCA, ASA)
A8: Efetividade do protocolo de controle glicêmico perioperatório | B8: ≥ 90% | C8: ADA / Endocrine Society / ERAS
A9: Saídas sem eventos relacionados ao ato anestésico | B9: ≥ 99% | C9: Padrão de alta confiabilidade (“zero harm”)
A10: Taxa de mortalidade associada à anestesia em até 48 horas | B10: Meta zero; vigilância ≤ 1/100.000 | C10: ASA, ANZCA, WFSA
A11: Taxa de mortalidade associada à anestesia em até 30 dias | B11: Meta zero; vigilância ≤ 2–5/100.000 | C11: NAP5 (UK), ANZCA, ESAIC
A12: Taxa de estratificação de risco anestésico (ASA) documentada | B12: ≥ 98–100% | C12: ASA Standards
... A18: Incidência de hipotermia não intencional até a alta anestésica | B18: ≤10% (ideal ≤5%); ≥90% com T° ≥ 36 °C no fim da anestesia | C18: NICE / SCIP-INF-10
